{
"meta":{"test_sets":[],"test_metrics":[],"learn_metrics":[{"best_value":"Min","name":"Logloss"}],"launch_mode":"Train","parameters":"","iteration_count":1000,"learn_sets":["learn"],"name":"experiment"},
"iterations":[
{"learn":[0.5062566531],"iteration":0,"passed_time":0.007315680596,"remaining_time":7.308364915},
{"learn":[0.413276941],"iteration":1,"passed_time":0.01462581945,"remaining_time":7.298283906},
{"learn":[0.3317339103],"iteration":2,"passed_time":0.02126440771,"remaining_time":7.066871496},
{"learn":[0.2888790175],"iteration":3,"passed_time":0.02807970665,"remaining_time":6.991846957},
{"learn":[0.2560428988],"iteration":4,"passed_time":0.03520805143,"remaining_time":7.006402234},
{"learn":[0.238696588],"iteration":5,"passed_time":0.04256631592,"remaining_time":7.051819671},
{"learn":[0.2249295882],"iteration":6,"passed_time":0.04974574471,"remaining_time":7.056789213},
{"learn":[0.2133616444],"iteration":7,"passed_time":0.05725334452,"remaining_time":7.09941472},
{"learn":[0.2055338536],"iteration":8,"passed_time":0.06471377704,"remaining_time":7.125705894},
{"learn":[0.1978937459],"iteration":9,"passed_time":0.07190516432,"remaining_time":7.118611267},
{"learn":[0.1911453986],"iteration":10,"passed_time":0.07906188446,"remaining_time":7.108382158},
{"learn":[0.1835356807],"iteration":11,"passed_time":0.08582872443,"remaining_time":7.066564978},
{"learn":[0.1769431058],"iteration":12,"passed_time":0.09377487174,"remaining_time":7.119676801},
{"learn":[0.1721418198],"iteration":13,"passed_time":0.101238596,"remaining_time":7.130089688},
{"learn":[0.1657000483],"iteration":14,"passed_time":0.10831244,"remaining_time":7.112516895},
{"learn":[0.1602792029],"iteration":15,"passed_time":0.1156479125,"remaining_time":7.112346621},
{"learn":[0.1574322553],"iteration":16,"passed_time":0.12297526,"remaining_time":7.110863561},
{"learn":[0.1530198676],"iteration":17,"passed_time":0.1302647735,"remaining_time":7.10666709},
{"learn":[0.1491984222],"iteration":18,"passed_time":0.1373886599,"remaining_time":7.093593441},
{"learn":[0.1463764529],"iteration":19,"passed_time":0.1447945917,"remaining_time":7.094934994},
{"learn":[0.1441356221],"iteration":20,"passed_time":0.1525161527,"remaining_time":7.110157786},
{"learn":[0.1419575957],"iteration":21,"passed_time":0.1595634131,"remaining_time":7.093318999},
{"learn":[0.1379079461],"iteration":22,"passed_time":0.1665386725,"remaining_time":7.074273174},
{"learn":[0.1345526668],"iteration":23,"passed_time":0.1741875242,"remaining_time":7.083625983},
{"learn":[0.1336001979],"iteration":24,"passed_time":0.1811262831,"remaining_time":7.06392504},
{"learn":[0.1326267767],"iteration":25,"passed_time":0.188341004,"remaining_time":7.055543765},
{"learn":[0.1319361623],"iteration":26,"passed_time":0.1955084743,"remaining_time":7.045546129},
{"learn":[0.1306749451],"iteration":27,"passed_time":0.2031272423,"remaining_time":7.051417124},
{"learn":[0.127704682],"iteration":28,"passed_time":0.2103280463,"remaining_time":7.042363206},
{"learn":[0.1269209359],"iteration":29,"passed_time":0.2176317268,"remaining_time":7.036759165},
{"learn":[0.1253914346],"iteration":30,"passed_time":0.2250610755,"remaining_time":7.034973619},
{"learn":[0.121437568],"iteration":31,"passed_time":0.2325846756,"remaining_time":7.035686436},
{"learn":[0.1200069499],"iteration":32,"passed_time":0.2398251052,"remaining_time":7.027602324},
{"learn":[0.119551814],"iteration":33,"passed_time":0.2470918684,"remaining_time":7.020316027},
{"learn":[0.1191307583],"iteration":34,"passed_time":0.2543141728,"remaining_time":7.01180505},
{"learn":[0.1150812505],"iteration":35,"passed_time":0.2617763137,"remaining_time":7.009787955},
{"learn":[0.11398534],"iteration":36,"passed_time":0.2690123265,"remaining_time":7.001591093},
{"learn":[0.1124993779],"iteration":37,"passed_time":0.2757197907,"remaining_time":6.980064175},
{"learn":[0.1098863342],"iteration":38,"passed_time":0.2826908834,"remaining_time":6.965793306},
{"learn":[0.1091729926],"iteration":39,"passed_time":0.2902177335,"remaining_time":6.965225603},
{"learn":[0.1088962108],"iteration":40,"passed_time":0.2973630785,"remaining_time":6.955394933},
{"learn":[0.1070591276],"iteration":41,"passed_time":0.304826011,"remaining_time":6.952936156},
{"learn":[0.105787971],"iteration":42,"passed_time":0.3128051171,"remaining_time":6.96173249},
{"learn":[0.1040454478],"iteration":43,"passed_time":0.320572887,"remaining_time":6.965174545},
{"learn":[0.103272936],"iteration":44,"passed_time":0.3280129859,"remaining_time":6.96116448},
{"learn":[0.1021956682],"iteration":45,"passed_time":0.335687213,"remaining_time":6.961860895},
{"learn":[0.1016143014],"iteration":46,"passed_time":0.3428093493,"remaining_time":6.951006594},
{"learn":[0.1009355155],"iteration":47,"passed_time":0.3499916115,"remaining_time":6.941500294},
{"learn":[0.09950524176],"iteration":48,"passed_time":0.3571727903,"remaining_time":6.932067828},
{"learn":[0.09730065795],"iteration":49,"passed_time":0.3647058488,"remaining_time":6.929411127},
{"learn":[0.09658063451],"iteration":50,"passed_time":0.3720152376,"remaining_time":6.922401186},
{"learn":[0.09634501141],"iteration":51,"passed_time":0.3792604173,"remaining_time":6.914209146},
{"learn":[0.09484830918],"iteration":52,"passed_time":0.387065021,"remaining_time":6.916048584},
{"learn":[0.09434197325],"iteration":53,"passed_time":0.3938173192,"remaining_time":6.899095998},
{"learn":[0.09418006363],"iteration":54,"passed_time":0.4008154955,"remaining_time":6.886738969},
{"learn":[0.09365999825],"iteration":55,"passed_time":0.4081155509,"remaining_time":6.879662144},
{"learn":[0.09322520951],"iteration":56,"passed_time":0.4151608946,"remaining_time":6.868363572},
{"learn":[0.0926954042],"iteration":57,"passed_time":0.4223263232,"remaining_time":6.859162008},
{"learn":[0.09247508132],"iteration":58,"passed_time":0.4293128327,"remaining_time":6.847175858},
{"learn":[0.09203464866],"iteration":59,"passed_time":0.4366410552,"remaining_time":6.840709864},
{"learn":[0.09067551798],"iteration":60,"passed_time":0.4439658609,"remaining_time":6.834163006},
{"learn":[0.08989167164],"iteration":61,"passed_time":0.4512425826,"remaining_time":6.826863589},
{"learn":[0.08947825595],"iteration":62,"passed_time":0.4583523855,"remaining_time":6.817082305},
{"learn":[0.08934705327],"iteration":63,"passed_time":0.4653773955,"remaining_time":6.80614441},
{"learn":[0.08923411169],"iteration":64,"passed_time":0.4726297836,"remaining_time":6.798597657},
{"learn":[0.08881324712],"iteration":65,"passed_time":0.4795297087,"remaining_time":6.786071938},
{"learn":[0.08831858886],"iteration":66,"passed_time":0.4871919356,"remaining_time":6.784329491},
{"learn":[0.0881815609],"iteration":67,"passed_time":0.4946164509,"remaining_time":6.779154887},
{"learn":[0.08772188459],"iteration":68,"passed_time":0.5022324689,"remaining_time":6.776498964},
{"learn":[0.08706462902],"iteration":69,"passed_time":0.5095966918,"remaining_time":6.770356048},
{"learn":[0.08694926697],"iteration":70,"passed_time":0.5170937498,"remaining_time":6.765916811},
{"learn":[0.08675486126],"iteration":71,"passed_time":0.5244196388,"remaining_time":6.759186456},
{"learn":[0.0866036046],"iteration":72,"passed_time":0.5318161955,"remaining_time":6.753337168},
{"learn":[0.08616902274],"iteration":73,"passed_time":0.5389459153,"remaining_time":6.744106994},
{"learn":[0.08588259451],"iteration":74,"passed_time":0.5461258441,"remaining_time":6.735552077},
{"learn":[0.08580445248],"iteration":75,"passed_time":0.553590735,"remaining_time":6.730497884},
{"learn":[0.08549312018],"iteration":76,"passed_time":0.5610032086,"remaining_time":6.724752747},
{"learn":[0.08453624547],"iteration":77,"passed_time":0.5686921441,"remaining_time":6.72223278},
{"learn":[0.08446231985],"iteration":78,"passed_time":0.5758119471,"remaining_time":6.712946877},
{"learn":[0.08427370186],"iteration":79,"passed_time":0.5829428336,"remaining_time":6.703842586},
{"learn":[0.08418619191],"iteration":80,"passed_time":0.5900700117,"remaining_time":6.694744947},
{"learn":[0.084092698],"iteration":81,"passed_time":0.5977818642,"remaining_time":6.69224087},
{"learn":[0.08379838732],"iteration":82,"passed_time":0.6053253812,"remaining_time":6.6877515},
{"learn":[0.08250414331],"iteration":83,"passed_time":0.6126388117,"remaining_time":6.680680375},
{"learn":[0.08209876328],"iteration":84,"passed_time":0.6201056193,"remaining_time":6.675254608},
{"learn":[0.08161229448],"iteration":85,"passed_time":0.6277462209,"remaining_time":6.671628441},
{"learn":[0.08151126519],"iteration":86,"passed_time":0.6350291511,"remaining_time":6.664156493},
{"learn":[0.08122783795],"iteration":87,"passed_time":0.642047161,"remaining_time":6.653943305},
{"learn":[0.08097030832],"iteration":88,"passed_time":0.6491547555,"remaining_time":6.644718902},
{"learn":[0.08070206465],"iteration":89,"passed_time":0.6568135657,"remaining_time":6.641114942},
{"learn":[0.0804162313],"iteration":90,"passed_time":0.6644321253,"remaining_time":6.637019801},
{"learn":[0.08035197727],"iteration":91,"passed_time":0.6714614688,"remaining_time":6.627032757},
{"learn":[0.08024371023],"iteration":92,"passed_time":0.6787808161,"remaining_time":6.619937636},
{"learn":[0.08015361709],"iteration":93,"passed_time":0.6859738284,"remaining_time":6.611620091},
{"learn":[0.07958571861],"iteration":94,"passed_time":0.6929694631,"remaining_time":6.601445938},
{"learn":[0.07948898163],"iteration":95,"passed_time":0.7000323903,"remaining_time":6.591971675},
{"learn":[0.07941996223],"iteration":96,"passed_time":0.707155985,"remaining_time":6.583111902},
{"learn":[0.07934473798],"iteration":97,"passed_time":0.7143332888,"remaining_time":6.574781903},
{"learn":[0.07925562384],"iteration":98,"passed_time":0.7212978814,"remaining_time":6.564539304},
{"learn":[0.07913567517],"iteration":99,"passed_time":0.7290282341,"remaining_time":6.561254107},
{"learn":[0.07901637517],"iteration":100,"passed_time":0.7361583706,"remaining_time":6.552538368},
{"learn":[0.0784296146],"iteration":101,"passed_time":0.7433753415,"remaining_time":6.544618203},
{"learn":[0.07805466191],"iteration":102,"passed_time":0.7517902034,"remaining_time":6.54714381},
{"learn":[0.07774817814],"iteration":103,"passed_time":0.7590648418,"remaining_time":6.53963556},
{"learn":[0.07766803707],"iteration":104,"passed_time":0.7664089811,"remaining_time":6.532724172},
{"learn":[0.07745650792],"iteration":105,"passed_time":0.773296781,"remaining_time":6.52195587},
{"learn":[0.07701206628],"iteration":106,"passed_time":0.7808410063,"remaining_time":6.516738492},
{"learn":[0.07670693548],"iteration":107,"passed_time":0.7884556492,"remaining_time":6.512059621},
{"learn":[0.0766564628],"iteration":108,"passed_time":0.7956463282,"remaining_time":6.50386127},
{"learn":[0.07640629237],"iteration":109,"passed_time":0.8032260956,"remaining_time":6.498829319},
{"learn":[0.0761928591],"iteration":110,"passed_time":0.8108563637,"remaining_time":6.494155922},
{"learn":[0.07613625501],"iteration":111,"passed_time":0.8180062504,"remaining_time":6.485620986},
{"learn":[0.07605936874],"iteration":112,"passed_time":0.8250222187,"remaining_time":6.476059363},
{"learn":[0.07587346374],"iteration":113,"passed_time":0.8321546052,"remaining_time":6.467447195},
{"learn":[0.07565412909],"iteration":114,"passed_time":0.8391462815,"remaining_time":6.457777905},
{"learn":[0.0755896388],"iteration":115,"passed_time":0.846001581,"remaining_time":6.447115496},
{"learn":[0.07540802215],"iteration":116,"passed_time":0.8528787557,"remaining_time":6.436683259},
{"learn":[0.07527126964],"iteration":117,"passed_time":0.86009756,"remaining_time":6.428864813},
{"learn":[0.0751196841],"iteration":118,"passed_time":0.8669711098,"remaining_time":6.418500401},
{"learn":[0.07505702482],"iteration":119,"passed_time":0.8742779569,"remaining_time":6.411371684},
{"learn":[0.07502480823],"iteration":120,"passed_time":0.8815410951,"remaining_time":6.403922501},
{"learn":[0.07486531727],"iteration":121,"passed_time":0.8885455216,"remaining_time":6.394614491},
{"learn":[0.0746942801],"iteration":122,"passed_time":0.8954569885,"remaining_time":6.384681129},
{"learn":[0.07459376295],"iteration":123,"passed_time":0.9021124103,"remaining_time":6.372987673},
{"learn":[0.0745004703],"iteration":124,"passed_time":0.9097796789,"remaining_time":6.368457752},
{"learn":[0.07443235115],"iteration":125,"passed_time":0.9172480699,"remaining_time":6.362498516},
{"learn":[0.07436974722],"iteration":126,"passed_time":0.9246647101,"remaining_time":6.356159779},
{"learn":[0.0742666933],"iteration":127,"passed_time":0.9315111761,"remaining_time":6.345919888},
{"learn":[0.07408236033],"iteration":128,"passed_time":0.9387236054,"remaining_time":6.338203568},
{"learn":[0.07390002454],"iteration":129,"passed_time":0.9460969951,"remaining_time":6.331572198},
{"learn":[0.0738055317],"iteration":130,"passed_time":0.953409634,"remaining_time":6.324526503},
{"learn":[0.0736586943],"iteration":131,"passed_time":0.960305684,"remaining_time":6.314737376},
{"learn":[0.07356823235],"iteration":132,"passed_time":0.9676164478,"remaining_time":6.30769519},
{"learn":[0.07353032321],"iteration":133,"passed_time":0.9745169979,"remaining_time":6.297997912},
{"learn":[0.07346271072],"iteration":134,"passed_time":0.9815823835,"remaining_time":6.289398235},
{"learn":[0.07336349114],"iteration":135,"passed_time":0.9884899337,"remaining_time":6.279818402},
{"learn":[0.07316041397],"iteration":136,"passed_time":0.9962321616,"remaining_time":6.275535441},
{"learn":[0.07280421972],"iteration":137,"passed_time":1.003750553,"remaining_time":6.26980418},
{"learn":[0.0725748784],"iteration":138,"passed_time":1.010825231,"remaining_time":6.261298731},
{"learn":[0.07231057055],"iteration":139,"passed_time":1.018232912,"remaining_time":6.254859319},
{"learn":[0.07219668002],"iteration":140,"passed_time":1.025374049,"remaining_time":6.246782327},
{"learn":[0.07210396765],"iteration":141,"passed_time":1.032904358,"remaining_time":6.241069991},
{"learn":[0.07206829189],"iteration":142,"passed_time":1.04012137,"remaining_time":6.233454645},
{"learn":[0.0719449693],"iteration":143,"passed_time":1.047130713,"remaining_time":6.224610351},
{"learn":[0.07182161532],"iteration":144,"passed_time":1.053993096,"remaining_time":6.214924809},
{"learn":[0.07172811287],"iteration":145,"passed_time":1.06078177,"remaining_time":6.204846791},
{"learn":[0.07160539255],"iteration":146,"passed_time":1.06779128,"remaining_time":6.196094977},
{"learn":[0.0714099502],"iteration":147,"passed_time":1.075298629,"remaining_time":6.190232651},
{"learn":[0.0712965361],"iteration":148,"passed_time":1.082535267,"remaining_time":6.182802097},
{"learn":[0.07123840468],"iteration":149,"passed_time":1.089638903,"remaining_time":6.174620453},
{"learn":[0.07111116339],"iteration":150,"passed_time":1.096835957,"remaining_time":6.16697833},
{"learn":[0.07096796589],"iteration":151,"passed_time":1.104174013,"remaining_time":6.160128706},
{"learn":[0.07085262109],"iteration":152,"passed_time":1.111631071,"remaining_time":6.153931484},
{"learn":[0.07077779383],"iteration":153,"passed_time":1.119443175,"remaining_time":6.149668349},
{"learn":[0.0706859452],"iteration":154,"passed_time":1.126449601,"remaining_time":6.140967181},
{"learn":[0.07063065855],"iteration":155,"passed_time":1.133947159,"remaining_time":6.134944887},
{"learn":[0.07058282451],"iteration":156,"passed_time":1.142438689,"remaining_time":6.134240858},
{"learn":[0.07052238149],"iteration":157,"passed_time":1.150710132,"remaining_time":6.132265387},
{"learn":[0.07021849069],"iteration":158,"passed_time":1.159598834,"remaining_time":6.133475591},
{"learn":[0.07012931385],"iteration":159,"passed_time":1.166599468,"remaining_time":6.124647209},
{"learn":[0.06988537442],"iteration":160,"passed_time":1.173936524,"remaining_time":6.117594682},
{"learn":[0.06975105175],"iteration":161,"passed_time":1.18115612,"remaining_time":6.109931041},
{"learn":[0.06962874824],"iteration":162,"passed_time":1.188451467,"remaining_time":6.102661828},
{"learn":[0.06957368232],"iteration":163,"passed_time":1.195420226,"remaining_time":6.093727496},
{"learn":[0.06950858516],"iteration":164,"passed_time":1.202804783,"remaining_time":6.086921175},
{"learn":[0.06944105938],"iteration":165,"passed_time":1.210138589,"remaining_time":6.07985291},
{"learn":[0.06932331555],"iteration":166,"passed_time":1.217593396,"remaining_time":6.073385025},
{"learn":[0.06922708155],"iteration":167,"passed_time":1.224649032,"remaining_time":6.064928538},
{"learn":[0.06908737801],"iteration":168,"passed_time":1.232716722,"remaining_time":6.061465067},
{"learn":[0.06903714929],"iteration":169,"passed_time":1.239837067,"remaining_time":6.053322151},
{"learn":[0.0689352691],"iteration":170,"passed_time":1.247431668,"remaining_time":6.047490367},
{"learn":[0.06885045394],"iteration":171,"passed_time":1.254378927,"remaining_time":6.038521811},
{"learn":[0.06869288482],"iteration":172,"passed_time":1.261801442,"remaining_time":6.031848514},
{"learn":[0.06866156154],"iteration":173,"passed_time":1.268923162,"remaining_time":6.023738689},
{"learn":[0.0686232172],"iteration":174,"passed_time":1.276028382,"remaining_time":6.01556237},
{"learn":[0.06856635325],"iteration":175,"passed_time":1.283096642,"remaining_time":6.007225188},
{"learn":[0.06845952857],"iteration":176,"passed_time":1.290415364,"remaining_time":6.000066921},
{"learn":[0.06837633684],"iteration":177,"passed_time":1.297714045,"remaining_time":5.992814297},
{"learn":[0.06814212605],"iteration":178,"passed_time":1.304755013,"remaining_time":5.98437914},
{"learn":[0.06807181894],"iteration":179,"passed_time":1.311753023,"remaining_time":5.975763772},
{"learn":[0.06794927645],"iteration":180,"passed_time":1.319382,"remaining_time":5.970021313},
{"learn":[0.06788164881],"iteration":181,"passed_time":1.327406398,"remaining_time":5.966035349},
{"learn":[0.06783046966],"iteration":182,"passed_time":1.334896248,"remaining_time":5.959618766},
{"learn":[0.06778914595],"iteration":183,"passed_time":1.341689546,"remaining_time":5.950101466},
{"learn":[0.0677211966],"iteration":184,"passed_time":1.348748307,"remaining_time":5.941783081},
{"learn":[0.06768219522],"iteration":185,"passed_time":1.356355783,"remaining_time":5.935879609},
{"learn":[0.06764601084],"iteration":186,"passed_time":1.363364709,"remaining_time":5.927355661},
{"learn":[0.06760774407],"iteration":187,"passed_time":1.370626931,"remaining_time":5.91994185},
{"learn":[0.06751499991],"iteration":188,"passed_time":1.377884069,"remaining_time":5.912507831},
{"learn":[0.06739825432],"iteration":189,"passed_time":1.385304084,"remaining_time":5.905770044},
{"learn":[0.06734091647],"iteration":190,"passed_time":1.392323594,"remaining_time":5.897328732},
{"learn":[0.0672546225],"iteration":191,"passed_time":1.399259937,"remaining_time":5.888552233},
{"learn":[0.06707106257],"iteration":192,"passed_time":1.406473366,"remaining_time":5.8809534},
{"learn":[0.06696839098],"iteration":193,"passed_time":1.413887589,"remaining_time":5.874192768},
{"learn":[0.06686951514],"iteration":194,"passed_time":1.421998656,"remaining_time":5.870302142},
{"learn":[0.06675565564],"iteration":195,"passed_time":1.429363212,"remaining_time":5.863306236},
{"learn":[0.06665215782],"iteration":196,"passed_time":1.43651139,"remaining_time":5.8554246},
{"learn":[0.06660851126],"iteration":197,"passed_time":1.443890072,"remaining_time":5.848484027},
{"learn":[0.06647814552],"iteration":198,"passed_time":1.451210877,"remaining_time":5.841306094},
{"learn":[0.06643521357],"iteration":199,"passed_time":1.458776353,"remaining_time":5.835105411},
{"learn":[0.06638897471],"iteration":200,"passed_time":1.466084367,"remaining_time":5.827867706},
{"learn":[0.06630810377],"iteration":201,"passed_time":1.473400047,"remaining_time":5.820659593},
{"learn":[0.06621641366],"iteration":202,"passed_time":1.480564643,"remaining_time":5.812857242},
{"learn":[0.06611459408],"iteration":203,"passed_time":1.488031117,"remaining_time":5.806239063},
{"learn":[0.06602487377],"iteration":204,"passed_time":1.494990668,"remaining_time":5.797646735},
{"learn":[0.06591816503],"iteration":205,"passed_time":1.502475642,"remaining_time":5.791095436},
{"learn":[0.06568184172],"iteration":206,"passed_time":1.509796698,"remaining_time":5.783907156},
{"learn":[0.06558878514],"iteration":207,"passed_time":1.51696221,"remaining_time":5.776125337},
{"learn":[0.06554175734],"iteration":208,"passed_time":1.525487156,"remaining_time":5.773494453},
{"learn":[0.06546977426],"iteration":209,"passed_time":1.534513818,"remaining_time":5.772694839},
{"learn":[0.06541982062],"iteration":210,"passed_time":1.541873208,"remaining_time":5.765582753},
{"learn":[0.06535486399],"iteration":211,"passed_time":1.54909597,"remaining_time":5.757960493},
{"learn":[0.06530482077],"iteration":212,"passed_time":1.556053354,"remaining_time":5.749361455},
{"learn":[0.0652632196],"iteration":213,"passed_time":1.563330701,"remaining_time":5.741952949},
{"learn":[0.0651858424],"iteration":214,"passed_time":1.570967553,"remaining_time":5.735858274},
{"learn":[0.06512601284],"iteration":215,"passed_time":1.578102898,"remaining_time":5.727929036},
{"learn":[0.06501805202],"iteration":216,"passed_time":1.585623414,"remaining_time":5.721396928},
{"learn":[0.06489849475],"iteration":217,"passed_time":1.59279901,"remaining_time":5.713618466},
{"learn":[0.0648401429],"iteration":218,"passed_time":1.600057856,"remaining_time":5.7061424},
{"learn":[0.06479773032],"iteration":219,"passed_time":1.607146909,"remaining_time":5.698066313},
{"learn":[0.0647033386],"iteration":220,"passed_time":1.613730455,"remaining_time":5.688217304},
{"learn":[0.06467639762],"iteration":221,"passed_time":1.620548504,"remaining_time":5.679219531},
{"learn":[0.06461471026],"iteration":222,"passed_time":1.628547235,"remaining_time":5.674355164},
{"learn":[0.06457003296],"iteration":223,"passed_time":1.635281741,"remaining_time":5.665083175},
{"learn":[0.06453973398],"iteration":224,"passed_time":1.642184166,"remaining_time":5.656412128},
{"learn":[0.06450194264],"iteration":225,"passed_time":1.649418137,"remaining_time":5.648892205},
{"learn":[0.06427670047],"iteration":226,"passed_time":1.657607121,"remaining_time":5.644626893},
{"learn":[0.06416572439],"iteration":227,"passed_time":1.665262181,"remaining_time":5.638519316},
{"learn":[0.06411284302],"iteration":228,"passed_time":1.672353526,"remaining_time":5.630500298},
{"learn":[0.06407665621],"iteration":229,"passed_time":1.679574413,"remaining_time":5.622923036},
{"learn":[0.06399697288],"iteration":230,"passed_time":1.686643466,"remaining_time":5.614843399},
{"learn":[0.06393077416],"iteration":231,"passed_time":1.694267692,"remaining_time":5.608610291},
{"learn":[0.06384921991],"iteration":232,"passed_time":1.70165679,"remaining_time":5.601591237},
{"learn":[0.06382095941],"iteration":233,"passed_time":1.708607716,"remaining_time":5.59313466},
{"learn":[0.06375840701],"iteration":234,"passed_time":1.715884646,"remaining_time":5.585752146},
{"learn":[0.0636579136],"iteration":235,"passed_time":1.72305745,"remaining_time":5.578033439},
{"learn":[0.06356262121],"iteration":236,"passed_time":1.731316976,"remaining_time":5.573817945},
{"learn":[0.06351408082],"iteration":237,"passed_time":1.738752158,"remaining_time":5.56692918},
{"learn":[0.06347469324],"iteration":238,"passed_time":1.74587117,"remaining_time":5.559029122},
{"learn":[0.06343304399],"iteration":239,"passed_time":1.753127141,"remaining_time":5.551569281},
{"learn":[0.06333470131],"iteration":240,"passed_time":1.760618574,"remaining_time":5.544852688},
{"learn":[0.06330005769],"iteration":241,"passed_time":1.768035089,"remaining_time":5.537895032},
{"learn":[0.06326339258],"iteration":242,"passed_time":1.775219393,"remaining_time":5.530210209},
{"learn":[0.06320190096],"iteration":243,"passed_time":1.782419614,"remaining_time":5.522578804},
{"learn":[0.06317900058],"iteration":244,"passed_time":1.789872088,"remaining_time":5.515728271},
{"learn":[0.06315923768],"iteration":245,"passed_time":1.796474134,"remaining_time":5.506266249},
{"learn":[0.06311532295],"iteration":246,"passed_time":1.803706564,"remaining_time":5.49874916},
{"learn":[0.06305728054],"iteration":247,"passed_time":1.810638906,"remaining_time":5.490324424},
{"learn":[0.06303151215],"iteration":248,"passed_time":1.817778751,"remaining_time":5.482537517},
{"learn":[0.06300126318],"iteration":249,"passed_time":1.824943096,"remaining_time":5.474829288},
{"learn":[0.06293464039],"iteration":250,"passed_time":1.832329236,"remaining_time":5.467787242},
{"learn":[0.06289737635],"iteration":251,"passed_time":1.839833252,"remaining_time":5.461092352},
{"learn":[0.06282332505],"iteration":252,"passed_time":1.847399561,"remaining_time":5.454574989},
{"learn":[0.0627176108],"iteration":253,"passed_time":1.85422036,"remaining_time":5.445859798},
{"learn":[0.0626721663],"iteration":254,"passed_time":1.861461623,"remaining_time":5.43838788},
{"learn":[0.06263662347],"iteration":255,"passed_time":1.868943181,"remaining_time":5.43161612},
{"learn":[0.06255996841],"iteration":256,"passed_time":1.876070817,"remaining_time":5.423815632},
{"learn":[0.06248353259],"iteration":257,"passed_time":1.883381706,"remaining_time":5.416547388},
{"learn":[0.06245809295],"iteration":258,"passed_time":1.890739929,"remaining_time":5.409414237},
{"learn":[0.06242625301],"iteration":259,"passed_time":1.897511769,"remaining_time":5.40061042},
{"learn":[0.0623806545],"iteration":260,"passed_time":1.904813908,"remaining_time":5.39332367},
{"learn":[0.06235856617],"iteration":261,"passed_time":1.911963086,"remaining_time":5.385605945},
{"learn":[0.06232393506],"iteration":262,"passed_time":1.918764427,"remaining_time":5.376917804},
{"learn":[0.06227453215],"iteration":263,"passed_time":1.925843479,"remaining_time":5.369018184},
{"learn":[0.06225252504],"iteration":264,"passed_time":1.933506664,"remaining_time":5.362744899},
{"learn":[0.06222459313],"iteration":265,"passed_time":1.940542133,"remaining_time":5.354729043},
{"learn":[0.06218968755],"iteration":266,"passed_time":1.947864647,"remaining_time":5.347508563},
{"learn":[0.06216044795],"iteration":267,"passed_time":1.954890157,"remaining_time":5.339476101},
{"learn":[0.06212978635],"iteration":268,"passed_time":1.962288297,"remaining_time":5.332463737},
{"learn":[0.06205431299],"iteration":269,"passed_time":1.969425017,"remaining_time":5.324741712},
{"learn":[0.06199039303],"iteration":270,"passed_time":1.976217691,"remaining_time":5.316098511},
{"learn":[0.06186193904],"iteration":271,"passed_time":1.984239006,"remaining_time":5.310757338},
{"learn":[0.06180082336],"iteration":272,"passed_time":1.991608312,"remaining_time":5.30366023},
{"learn":[0.06177738643],"iteration":273,"passed_time":1.99837086,"remaining_time":5.294953447},
{"learn":[0.06175536825],"iteration":274,"passed_time":2.005465996,"remaining_time":5.287137626},
{"learn":[0.06168693452],"iteration":275,"passed_time":2.012944054,"remaining_time":5.280331504},
{"learn":[0.06165319784],"iteration":276,"passed_time":2.019990398,"remaining_time":5.272393709},
{"learn":[0.06163469616],"iteration":277,"passed_time":2.027383746,"remaining_time":5.265363541},
{"learn":[0.06160062555],"iteration":278,"passed_time":2.035381935,"remaining_time":5.259893819},
{"learn":[0.06150252095],"iteration":279,"passed_time":2.042375487,"remaining_time":5.25182268},
{"learn":[0.06142176611],"iteration":280,"passed_time":2.049755377,"remaining_time":5.244747743},
{"learn":[0.06135785634],"iteration":281,"passed_time":2.056983223,"remaining_time":5.237283524},
{"learn":[0.06131267219],"iteration":282,"passed_time":2.064360154,"remaining_time":5.230198694},
{"learn":[0.06126560234],"iteration":283,"passed_time":2.071564458,"remaining_time":5.222676592},
{"learn":[0.06122477611],"iteration":284,"passed_time":2.078954765,"remaining_time":5.215623357},
{"learn":[0.06119214487],"iteration":285,"passed_time":2.086024442,"remaining_time":5.207767314},
{"learn":[0.06117075311],"iteration":286,"passed_time":2.093321456,"remaining_time":5.200481526},
{"learn":[0.06114721949],"iteration":287,"passed_time":2.100245048,"remaining_time":5.192272479},
{"learn":[0.06107395213],"iteration":288,"passed_time":2.107690647,"remaining_time":5.185356574},
{"learn":[0.06103826384],"iteration":289,"passed_time":2.114590364,"remaining_time":5.177100545},
{"learn":[0.06099271413],"iteration":290,"passed_time":2.121761751,"remaining_time":5.169515743},
{"learn":[0.06093273266],"iteration":291,"passed_time":2.128859512,"remaining_time":5.161755254},
{"learn":[0.06089428822],"iteration":292,"passed_time":2.136541572,"remaining_time":5.155409186},
{"learn":[0.0608470131],"iteration":293,"passed_time":2.143533832,"remaining_time":5.147397569},
{"learn":[0.06080767254],"iteration":294,"passed_time":2.150678093,"remaining_time":5.139756121},
{"learn":[0.06076141104],"iteration":295,"passed_time":2.158291528,"remaining_time":5.133233904},
{"learn":[0.06070857199],"iteration":296,"passed_time":2.165728543,"remaining_time":5.126286754},
{"learn":[0.06065209072],"iteration":297,"passed_time":2.172745637,"remaining_time":5.118347104},
{"learn":[0.06060777284],"iteration":298,"passed_time":2.180800911,"remaining_time":5.11284762},
{"learn":[0.06058903983],"iteration":299,"passed_time":2.187587001,"remaining_time":5.104369668},
{"learn":[0.06056964773],"iteration":300,"passed_time":2.194552718,"remaining_time":5.0963201},
{"learn":[0.06053349545],"iteration":301,"passed_time":2.201931025,"remaining_time":5.089231309},
{"learn":[0.06051280755],"iteration":302,"passed_time":2.208623572,"remaining_time":5.080563134},
{"learn":[0.06048740187],"iteration":303,"passed_time":2.215457538,"remaining_time":5.072231732},
{"learn":[0.06043688648],"iteration":304,"passed_time":2.222454964,"remaining_time":5.064282624},
{"learn":[0.06040820415],"iteration":305,"passed_time":2.229744811,"remaining_time":5.057002938},
{"learn":[0.06034989084],"iteration":306,"passed_time":2.237661625,"remaining_time":5.051138456},
{"learn":[0.06031837941],"iteration":307,"passed_time":2.24518235,"remaining_time":5.044370734},
{"learn":[0.06026269393],"iteration":308,"passed_time":2.252545656,"remaining_time":5.037246111},
{"learn":[0.06022662321],"iteration":309,"passed_time":2.259365705,"remaining_time":5.028910763},
{"learn":[0.06019238163],"iteration":310,"passed_time":2.266416049,"remaining_time":5.021095362},
{"learn":[0.06018097197],"iteration":311,"passed_time":2.273437184,"remaining_time":5.013220457},
{"learn":[0.06015015788],"iteration":312,"passed_time":2.280675947,"remaining_time":5.005828675},
{"learn":[0.06009364092],"iteration":313,"passed_time":2.287954252,"remaining_time":4.998524257},
{"learn":[0.06006873008],"iteration":314,"passed_time":2.295285933,"remaining_time":4.991336076},
{"learn":[0.0600510747],"iteration":315,"passed_time":2.302402319,"remaining_time":4.983680969},
{"learn":[0.06000052212],"iteration":316,"passed_time":2.309501705,"remaining_time":4.975992632},
{"learn":[0.05993452239],"iteration":317,"passed_time":2.316697884,"remaining_time":4.968515588},
{"learn":[0.05988244325],"iteration":318,"passed_time":2.32428161,"remaining_time":4.961867637},
{"learn":[0.05983973763],"iteration":319,"passed_time":2.331625499,"remaining_time":4.954704186},
{"learn":[0.05980118887],"iteration":320,"passed_time":2.339132516,"remaining_time":4.947884667},
{"learn":[0.05977683918],"iteration":321,"passed_time":2.346241777,"remaining_time":4.940223368},
{"learn":[0.059725449],"iteration":322,"passed_time":2.352959991,"remaining_time":4.931745864},
{"learn":[0.0596854212],"iteration":323,"passed_time":2.35991375,"remaining_time":4.923770664},
{"learn":[0.05960839498],"iteration":324,"passed_time":2.367032011,"remaining_time":4.916143408},
{"learn":[0.05956832934],"iteration":325,"passed_time":2.374297025,"remaining_time":4.908822683},
{"learn":[0.05952242691],"iteration":326,"passed_time":2.381275659,"remaining_time":4.900912901},
{"learn":[0.05949699311],"iteration":327,"passed_time":2.388192959,"remaining_time":4.892883136},
{"learn":[0.05942617505],"iteration":328,"passed_time":2.3956401,"remaining_time":4.885940751},
{"learn":[0.05941100084],"iteration":329,"passed_time":2.402941531,"remaining_time":4.878699471},
{"learn":[0.05937091833],"iteration":330,"passed_time":2.410066959,"remaining_time":4.871102101},
{"learn":[0.0593485112],"iteration":331,"passed_time":2.417295513,"remaining_time":4.863715068},
{"learn":[0.05932371293],"iteration":332,"passed_time":2.42437144,"remaining_time":4.856023276},
{"learn":[0.05928215645],"iteration":333,"passed_time":2.431483452,"remaining_time":4.848407122},
{"learn":[0.05925728175],"iteration":334,"passed_time":2.439300764,"remaining_time":4.842194054},
{"learn":[0.05923005822],"iteration":335,"passed_time":2.446489818,"remaining_time":4.834729878},
{"learn":[0.05921428361],"iteration":336,"passed_time":2.453797915,"remaining_time":4.827501536},
{"learn":[0.05916798297],"iteration":337,"passed_time":2.461495059,"remaining_time":4.821034701},
{"learn":[0.05914201044],"iteration":338,"passed_time":2.468325025,"remaining_time":4.812869739},
{"learn":[0.05910872817],"iteration":339,"passed_time":2.475561829,"remaining_time":4.805502375},
{"learn":[0.05905369193],"iteration":340,"passed_time":2.482737091,"remaining_time":4.798016842},
{"learn":[0.0589790839],"iteration":341,"passed_time":2.49011769,"remaining_time":4.790928186},
{"learn":[0.05894475389],"iteration":342,"passed_time":2.497038282,"remaining_time":4.782956708},
{"learn":[0.05892168015],"iteration":343,"passed_time":2.504365254,"remaining_time":4.775766298},
{"learn":[0.05889293711],"iteration":344,"passed_time":2.51135618,"remaining_time":4.767937096},
{"learn":[0.05885143643],"iteration":345,"passed_time":2.518573651,"remaining_time":4.760540948},
{"learn":[0.05883965001],"iteration":346,"passed_time":2.525847831,"remaining_time":4.753252547},
{"learn":[0.05882104839],"iteration":347,"passed_time":2.532979593,"remaining_time":4.745697398},
{"learn":[0.05879274355],"iteration":348,"passed_time":2.540082979,"remaining_time":4.738091746},
{"learn":[0.05876872067],"iteration":349,"passed_time":2.547441743,"remaining_time":4.730963238},
{"learn":[0.05873981995],"iteration":350,"passed_time":2.554750424,"remaining_time":4.723740812},
{"learn":[0.05872270123],"iteration":351,"passed_time":2.561907936,"remaining_time":4.716239609},
{"learn":[0.05870078461],"iteration":352,"passed_time":2.569005322,"remaining_time":4.708630151},
{"learn":[0.05865409891],"iteration":353,"passed_time":2.576321211,"remaining_time":4.701422322},
{"learn":[0.05862516453],"iteration":354,"passed_time":2.5830323,"remaining_time":4.693115024},
{"learn":[0.05859181792],"iteration":355,"passed_time":2.589849682,"remaining_time":4.685008976},
{"learn":[0.05856605612],"iteration":356,"passed_time":2.596917568,"remaining_time":4.677361334},
{"learn":[0.058513316],"iteration":357,"passed_time":2.604214456,"remaining_time":4.670127601},
{"learn":[0.05848775079],"iteration":358,"passed_time":2.61138426,"remaining_time":4.662666604},
{"learn":[0.05847021246],"iteration":359,"passed_time":2.61814085,"remaining_time":4.654472622},
{"learn":[0.0584484038],"iteration":360,"passed_time":2.625161027,"remaining_time":4.646753175},
{"learn":[0.05843375249],"iteration":361,"passed_time":2.631984034,"remaining_time":4.638690093},
{"learn":[0.05837806226],"iteration":362,"passed_time":2.639542509,"remaining_time":4.631924459},
{"learn":[0.05829317738],"iteration":363,"passed_time":2.646944816,"remaining_time":4.624881602},
{"learn":[0.05822829641],"iteration":364,"passed_time":2.653849575,"remaining_time":4.616971178},
{"learn":[0.05820133523],"iteration":365,"passed_time":2.661082088,"remaining_time":4.609633999},
{"learn":[0.05817707788],"iteration":366,"passed_time":2.668278392,"remaining_time":4.602234937},
{"learn":[0.05812665133],"iteration":367,"passed_time":2.675601406,"remaining_time":4.595054588},
{"learn":[0.05808448098],"iteration":368,"passed_time":2.682627207,"remaining_time":4.587365224},
{"learn":[0.05806213291],"iteration":369,"passed_time":2.689558216,"remaining_time":4.579518044},
{"learn":[0.05804222031],"iteration":370,"passed_time":2.696567976,"remaining_time":4.571809318},
{"learn":[0.05798751817],"iteration":371,"passed_time":2.703443984,"remaining_time":4.563878554},
{"learn":[0.05796247126],"iteration":372,"passed_time":2.710763623,"remaining_time":4.556699173},
{"learn":[0.05791527519],"iteration":373,"passed_time":2.7178123,"remaining_time":4.549065508},
{"learn":[0.05789444797],"iteration":374,"passed_time":2.725292233,"remaining_time":4.542153721},
{"learn":[0.05777091666],"iteration":375,"passed_time":2.732810333,"remaining_time":4.535302254},
{"learn":[0.05772845299],"iteration":376,"passed_time":2.740212098,"remaining_time":4.528255005},
{"learn":[0.05766296278],"iteration":377,"passed_time":2.748176204,"remaining_time":4.522131214},
{"learn":[0.05764491012],"iteration":378,"passed_time":2.75492496,"remaining_time":4.514006333},
{"learn":[0.05761030158],"iteration":379,"passed_time":2.762145015,"remaining_time":4.506657655},
{"learn":[0.05760006624],"iteration":380,"passed_time":2.769179525,"remaining_time":4.499008204},
{"learn":[0.05755527218],"iteration":381,"passed_time":2.776414163,"remaining_time":4.491685739},
{"learn":[0.0575341717],"iteration":382,"passed_time":2.783847095,"remaining_time":4.484683179},
{"learn":[0.05750981934],"iteration":383,"passed_time":2.791445612,"remaining_time":4.477944003},
{"learn":[0.05749890641],"iteration":384,"passed_time":2.798709584,"remaining_time":4.470665959},
{"learn":[0.05746671241],"iteration":385,"passed_time":2.806234642,"remaining_time":4.463803291},
{"learn":[0.05745499371],"iteration":386,"passed_time":2.813574157,"remaining_time":4.456643302},
{"learn":[0.05742688552],"iteration":387,"passed_time":2.820834086,"remaining_time":4.449356858},
{"learn":[0.05739122505],"iteration":388,"passed_time":2.827980348,"remaining_time":4.441892012},
{"learn":[0.05737148983],"iteration":389,"passed_time":2.835466073,"remaining_time":4.434959755},
{"learn":[0.05735090339],"iteration":390,"passed_time":2.842469916,"remaining_time":4.427274114},
{"learn":[0.05731544816],"iteration":391,"passed_time":2.850488356,"remaining_time":4.421165613},
{"learn":[0.05729147119],"iteration":392,"passed_time":2.857374281,"remaining_time":4.413298189},
{"learn":[0.05724874643],"iteration":393,"passed_time":2.864498375,"remaining_time":4.40580207},
{"learn":[0.05722869274],"iteration":394,"passed_time":2.871818473,"remaining_time":4.39860804},
{"learn":[0.0571733049],"iteration":395,"passed_time":2.878720648,"remaining_time":4.390775937},
{"learn":[0.05713500456],"iteration":396,"passed_time":2.886030662,"remaining_time":4.383567982},
{"learn":[0.0571162719],"iteration":397,"passed_time":2.893146548,"remaining_time":4.376065884},
{"learn":[0.05709822962],"iteration":398,"passed_time":2.89992868,"remaining_time":4.368062999},
{"learn":[0.05708989148],"iteration":399,"passed_time":2.90721886,"remaining_time":4.36082829},
{"learn":[0.05705309093],"iteration":400,"passed_time":2.914336288,"remaining_time":4.353335253},
{"learn":[0.05700680775],"iteration":401,"passed_time":2.921922472,"remaining_time":4.346541389},
{"learn":[0.05697777288],"iteration":402,"passed_time":2.929089651,"remaining_time":4.339122882},
{"learn":[0.05695881427],"iteration":403,"passed_time":2.93606716,"remaining_time":4.331425811},
{"learn":[0.05694192575],"iteration":404,"passed_time":2.943261172,"remaining_time":4.324050364},
{"learn":[0.05692159369],"iteration":405,"passed_time":2.950954275,"remaining_time":4.317406008},
{"learn":[0.05689191343],"iteration":406,"passed_time":2.958557042,"remaining_time":4.31062488},
{"learn":[0.05687496782],"iteration":407,"passed_time":2.96567447,"remaining_time":4.303135506},
{"learn":[0.05684090853],"iteration":408,"passed_time":2.97306861,"remaining_time":4.296047796},
{"learn":[0.05681680068],"iteration":409,"passed_time":2.980196664,"remaining_time":4.288575687},
{"learn":[0.05680070934],"iteration":410,"passed_time":2.987484385,"remaining_time":4.281334071},
{"learn":[0.05676058648],"iteration":411,"passed_time":2.994854858,"remaining_time":4.274210332},
{"learn":[0.0567454036],"iteration":412,"passed_time":3.001750117,"remaining_time":4.266409972},
{"learn":[0.05673099963],"iteration":413,"passed_time":3.009137465,"remaining_time":4.259310518},
{"learn":[0.05668797056],"iteration":414,"passed_time":3.01651323,"remaining_time":4.252193348},
{"learn":[0.05667091675],"iteration":415,"passed_time":3.023665408,"remaining_time":4.244761054},
{"learn":[0.05661698695],"iteration":416,"passed_time":3.031363302,"remaining_time":4.238093058},
{"learn":[0.05655677342],"iteration":417,"passed_time":3.038585023,"remaining_time":4.230757137},
{"learn":[0.05653038124],"iteration":418,"passed_time":3.045623992,"remaining_time":4.223168351},
{"learn":[0.05650136433],"iteration":419,"passed_time":3.05311655,"remaining_time":4.216208569},
{"learn":[0.05647719461],"iteration":420,"passed_time":3.060557065,"remaining_time":4.209174681},
{"learn":[0.05645966658],"iteration":421,"passed_time":3.06828671,"remaining_time":4.202534877},
{"learn":[0.05643147389],"iteration":422,"passed_time":3.075392679,"remaining_time":4.195039186},
{"learn":[0.05639709981],"iteration":423,"passed_time":3.082753694,"remaining_time":4.18789181},
{"learn":[0.05634971729],"iteration":424,"passed_time":3.090255293,"remaining_time":4.180933632},
{"learn":[0.05634197625],"iteration":425,"passed_time":3.097108593,"remaining_time":4.173099372},
{"learn":[0.05632189232],"iteration":426,"passed_time":3.104962072,"remaining_time":4.166611867},
{"learn":[0.0562938553],"iteration":427,"passed_time":3.11192154,"remaining_time":4.158923179},
{"learn":[0.05625387231],"iteration":428,"passed_time":3.119457098,"remaining_time":4.152004669},
{"learn":[0.0562242854],"iteration":429,"passed_time":3.126234063,"remaining_time":4.144077712},
{"learn":[0.05620286],"iteration":430,"passed_time":3.133191114,"remaining_time":4.136393838},
{"learn":[0.05617716126],"iteration":431,"passed_time":3.140588754,"remaining_time":4.129292621},
{"learn":[0.05615779328],"iteration":432,"passed_time":3.147498554,"remaining_time":4.121551225},
{"learn":[0.05614163616],"iteration":433,"passed_time":3.155889458,"remaining_time":4.115745237},
{"learn":[0.05611671244],"iteration":434,"passed_time":3.163135471,"remaining_time":4.108440324},
{"learn":[0.05609210568],"iteration":435,"passed_time":3.170017896,"remaining_time":4.100665351},
{"learn":[0.05607238088],"iteration":436,"passed_time":3.177150199,"remaining_time":4.093216389},
{"learn":[0.05605733519],"iteration":437,"passed_time":3.183847663,"remaining_time":4.085210928},
{"learn":[0.05598383798],"iteration":438,"passed_time":3.191260386,"remaining_time":4.078125459},
{"learn":[0.05595257325],"iteration":439,"passed_time":3.198471357,"remaining_time":4.070781727},
{"learn":[0.05591671174],"iteration":440,"passed_time":3.206171793,"remaining_time":4.06405903},
{"learn":[0.05589726227],"iteration":441,"passed_time":3.213715101,"remaining_time":4.057133544},
{"learn":[0.05588263318],"iteration":442,"passed_time":3.220557984,"remaining_time":4.049324599},
{"learn":[0.0558658509],"iteration":443,"passed_time":3.227880415,"remaining_time":4.042120519},
{"learn":[0.05582565819],"iteration":444,"passed_time":3.23505076,"remaining_time":4.034726229},
{"learn":[0.05580518703],"iteration":445,"passed_time":3.242193438,"remaining_time":4.027298576},
{"learn":[0.05579267598],"iteration":446,"passed_time":3.249129072,"remaining_time":4.019616056},
{"learn":[0.05575751065],"iteration":447,"passed_time":3.257382182,"remaining_time":4.013560189},
{"learn":[0.05574168593],"iteration":448,"passed_time":3.264994992,"remaining_time":4.006708776},
{"learn":[0.05572751457],"iteration":449,"passed_time":3.272332672,"remaining_time":3.999517711},
{"learn":[0.05568916565],"iteration":450,"passed_time":3.279320807,"remaining_time":3.991900495},
{"learn":[0.05566258922],"iteration":451,"passed_time":3.286323692,"remaining_time":3.984303945},
{"learn":[0.05565199129],"iteration":452,"passed_time":3.29309199,"remaining_time":3.976426752},
{"learn":[0.05562162216],"iteration":453,"passed_time":3.300420838,"remaining_time":3.969228584},
{"learn":[0.05558517947],"iteration":454,"passed_time":3.30797723,"remaining_time":3.962302396},
{"learn":[0.05553101945],"iteration":455,"passed_time":3.315225493,"remaining_time":3.955005851},
{"learn":[0.05551453322],"iteration":456,"passed_time":3.322449672,"remaining_time":3.947680901},
{"learn":[0.05546914887],"iteration":457,"passed_time":3.329746477,"remaining_time":3.940442338},
{"learn":[0.05544543699],"iteration":458,"passed_time":3.336749737,"remaining_time":3.932857533},
{"learn":[0.05542178545],"iteration":459,"passed_time":3.344051376,"remaining_time":3.925625528},
{"learn":[0.05539673069],"iteration":460,"passed_time":3.35133814,"remaining_time":3.918375829},
{"learn":[0.05537841453],"iteration":461,"passed_time":3.358013145,"remaining_time":3.910413576},
{"learn":[0.0553681537],"iteration":462,"passed_time":3.365261866,"remaining_time":3.903122294},
{"learn":[0.05535120926],"iteration":463,"passed_time":3.372502088,"remaining_time":3.895821377},
{"learn":[0.05532912532],"iteration":464,"passed_time":3.379672766,"remaining_time":3.88844071},
{"learn":[0.05530785752],"iteration":465,"passed_time":3.387327576,"remaining_time":3.881615721},
{"learn":[0.0552691046],"iteration":466,"passed_time":3.394625173,"remaining_time":3.874379481},
{"learn":[0.0552520727],"iteration":467,"passed_time":3.402056564,"remaining_time":3.867295068},
{"learn":[0.05521950443],"iteration":468,"passed_time":3.409344994,"remaining_time":3.860047317},
{"learn":[0.05515491436],"iteration":469,"passed_time":3.416820385,"remaining_time":3.853010222},
{"learn":[0.05512993545],"iteration":470,"passed_time":3.424034814,"remaining_time":3.845678167},
{"learn":[0.05509756036],"iteration":471,"passed_time":3.43133187,"remaining_time":3.838439041},
{"learn":[0.05500818783],"iteration":472,"passed_time":3.439084223,"remaining_time":3.831706946},
{"learn":[0.05499348502],"iteration":473,"passed_time":3.44615365,"remaining_time":3.8242127},
{"learn":[0.05495645238],"iteration":474,"passed_time":3.453271953,"remaining_time":3.816774264},
{"learn":[0.05493800414],"iteration":475,"passed_time":3.460360047,"remaining_time":3.809303918},
{"learn":[0.05490730365],"iteration":476,"passed_time":3.468401613,"remaining_time":3.802880594},
{"learn":[0.05488517817],"iteration":477,"passed_time":3.475778711,"remaining_time":3.795724868},
{"learn":[0.05483937683],"iteration":478,"passed_time":3.48275847,"remaining_time":3.788136039},
{"learn":[0.0548170126],"iteration":479,"passed_time":3.490165235,"remaining_time":3.781012338},
{"learn":[0.05479433932],"iteration":480,"passed_time":3.497502083,"remaining_time":3.773812019},
{"learn":[0.05478148424],"iteration":481,"passed_time":3.504476884,"remaining_time":3.766222045},
{"learn":[0.05477476429],"iteration":482,"passed_time":3.511524394,"remaining_time":3.758712447},
{"learn":[0.05474693153],"iteration":483,"passed_time":3.518639114,"remaining_time":3.751276411},
{"learn":[0.0547109632],"iteration":484,"passed_time":3.525803334,"remaining_time":3.743894262},
{"learn":[0.0546905356],"iteration":485,"passed_time":3.532974263,"remaining_time":3.736520105},
{"learn":[0.0546723383],"iteration":486,"passed_time":3.540027981,"remaining_time":3.729023315},
{"learn":[0.0546579539],"iteration":487,"passed_time":3.547463039,"remaining_time":3.721928434},
{"learn":[0.05463189279],"iteration":488,"passed_time":3.554763802,"remaining_time":3.714691826},
{"learn":[0.0545979187],"iteration":489,"passed_time":3.562496572,"remaining_time":3.707904595},
{"learn":[0.05453608535],"iteration":490,"passed_time":3.570247633,"remaining_time":3.701132475},
{"learn":[0.05451825911],"iteration":491,"passed_time":3.577800984,"remaining_time":3.694152235},
{"learn":[0.0545100279],"iteration":492,"passed_time":3.584490198,"remaining_time":3.686280994},
{"learn":[0.05449778124],"iteration":493,"passed_time":3.591362914,"remaining_time":3.678602499},
{"learn":[0.05445205036],"iteration":494,"passed_time":3.598395091,"remaining_time":3.671089941},
{"learn":[0.05443688882],"iteration":495,"passed_time":3.605588645,"remaining_time":3.6637433},
{"learn":[0.05442017526],"iteration":496,"passed_time":3.613126078,"remaining_time":3.656745307},
{"learn":[0.0543804916],"iteration":497,"passed_time":3.619945377,"remaining_time":3.649021244},
{"learn":[0.0543674666],"iteration":498,"passed_time":3.6272621,"remaining_time":3.641800224},
{"learn":[0.0543503309],"iteration":499,"passed_time":3.636568182,"remaining_time":3.636568182},
{"learn":[0.0543292655],"iteration":500,"passed_time":3.643152436,"remaining_time":3.628608913},
{"learn":[0.05431161969],"iteration":501,"passed_time":3.650070903,"remaining_time":3.620986673},
{"learn":[0.0542838567],"iteration":502,"passed_time":3.65691116,"remaining_time":3.613289954},
{"learn":[0.05427813373],"iteration":503,"passed_time":3.664081422,"remaining_time":3.6059214},
{"learn":[0.05425025749],"iteration":504,"passed_time":3.672058529,"remaining_time":3.599344498},
{"learn":[0.0542452642],"iteration":505,"passed_time":3.679229541,"remaining_time":3.591975085},
{"learn":[0.0542283717],"iteration":506,"passed_time":3.686572846,"remaining_time":3.584773991},
{"learn":[0.05420972164],"iteration":507,"passed_time":3.693621024,"remaining_time":3.577286503},
{"learn":[0.05419363856],"iteration":508,"passed_time":3.700867953,"remaining_time":3.569992466},
{"learn":[0.05416005214],"iteration":509,"passed_time":3.708033298,"remaining_time":3.562620228},
{"learn":[0.05408571757],"iteration":510,"passed_time":3.715202227,"remaining_time":3.555252229},
{"learn":[0.05407408862],"iteration":511,"passed_time":3.722521074,"remaining_time":3.548027899},
{"learn":[0.05404980551],"iteration":512,"passed_time":3.730006299,"remaining_time":3.540961145},
{"learn":[0.05402829796],"iteration":513,"passed_time":3.737377772,"remaining_time":3.533785208},
{"learn":[0.05401278373],"iteration":514,"passed_time":3.744659494,"remaining_time":3.526523989},
{"learn":[0.05399496038],"iteration":515,"passed_time":3.751922007,"remaining_time":3.519244673},
{"learn":[0.05398223294],"iteration":516,"passed_time":3.759004893,"remaining_time":3.511797608},
{"learn":[0.0539627811],"iteration":517,"passed_time":3.766024319,"remaining_time":3.5042929},
{"learn":[0.05393735102],"iteration":518,"passed_time":3.773766464,"remaining_time":3.497459864},
{"learn":[0.05391165985],"iteration":519,"passed_time":3.780659431,"remaining_time":3.489839474},
{"learn":[0.05389252356],"iteration":520,"passed_time":3.788110571,"remaining_time":3.482735055},
{"learn":[0.05388072672],"iteration":521,"passed_time":3.795170999,"remaining_time":3.475271527},
{"learn":[0.05386047118],"iteration":522,"passed_time":3.802391761,"remaining_time":3.467955775},
{"learn":[0.05382309063],"iteration":523,"passed_time":3.809849735,"remaining_time":3.460855867},
{"learn":[0.05378989454],"iteration":524,"passed_time":3.816791619,"remaining_time":3.453287656},
{"learn":[0.05374647493],"iteration":525,"passed_time":3.824017674,"remaining_time":3.445977904},
{"learn":[0.05372152169],"iteration":526,"passed_time":3.831018267,"remaining_time":3.438466111},
{"learn":[0.05369201187],"iteration":527,"passed_time":3.838083486,"remaining_time":3.431014025},
{"learn":[0.05366523416],"iteration":528,"passed_time":3.845606919,"remaining_time":3.423971378},
{"learn":[0.05364241933],"iteration":529,"passed_time":3.852979934,"remaining_time":3.416793526},
{"learn":[0.05362863881],"iteration":530,"passed_time":3.859943193,"remaining_time":3.409253027},
{"learn":[0.05360783966],"iteration":531,"passed_time":3.867238248,"remaining_time":3.402006579},
{"learn":[0.05359582363],"iteration":532,"passed_time":3.874368802,"remaining_time":3.394615817},
{"learn":[0.05355839092],"iteration":533,"passed_time":3.882187781,"remaining_time":3.38782679},
{"learn":[0.05354234792],"iteration":534,"passed_time":3.889095247,"remaining_time":3.380241664},
{"learn":[0.05352778628],"iteration":535,"passed_time":3.895947422,"remaining_time":3.372611201},
{"learn":[0.0534991075],"iteration":536,"passed_time":3.902812805,"remaining_time":3.364995025},
{"learn":[0.05348063388],"iteration":537,"passed_time":3.910081068,"remaining_time":3.357727609},
{"learn":[0.05346357975],"iteration":538,"passed_time":3.91713337,"remaining_time":3.35027548},
{"learn":[0.05343288426],"iteration":539,"passed_time":3.924459551,"remaining_time":3.343058136},
{"learn":[0.05341307551],"iteration":540,"passed_time":3.931566979,"remaining_time":3.335654793},
{"learn":[0.05337666616],"iteration":541,"passed_time":3.938749741,"remaining_time":3.328316202},
{"learn":[0.05335525475],"iteration":542,"passed_time":3.945822752,"remaining_time":3.320885815},
{"learn":[0.05332916719],"iteration":543,"passed_time":3.95320735,"remaining_time":3.313717926},
{"learn":[0.05331568179],"iteration":544,"passed_time":3.960672824,"remaining_time":3.306616761},
{"learn":[0.05330712573],"iteration":545,"passed_time":3.967897503,"remaining_time":3.299314041},
{"learn":[0.05329367309],"iteration":546,"passed_time":3.974967264,"remaining_time":3.29188331},
{"learn":[0.05324454781],"iteration":547,"passed_time":3.983156206,"remaining_time":3.285377017},
{"learn":[0.05323160545],"iteration":548,"passed_time":3.990287259,"remaining_time":3.277995545},
{"learn":[0.0531836494],"iteration":549,"passed_time":3.997864652,"remaining_time":3.27098017},
{"learn":[0.05316600469],"iteration":550,"passed_time":4.005209416,"remaining_time":3.26377319},
{"learn":[0.0531555311],"iteration":551,"passed_time":4.012261302,"remaining_time":3.256328013},
{"learn":[0.05314109163],"iteration":552,"passed_time":4.020093947,"remaining_time":3.249515361},
{"learn":[0.05310929346],"iteration":553,"passed_time":4.027395294,"remaining_time":3.242271302},
{"learn":[0.05309857335],"iteration":554,"passed_time":4.034047883,"remaining_time":3.234506861},
{"learn":[0.05308125156],"iteration":555,"passed_time":4.040878432,"remaining_time":3.226888532},
{"learn":[0.05305744541],"iteration":556,"passed_time":4.048169654,"remaining_time":3.21963942},
{"learn":[0.05303780922],"iteration":557,"passed_time":4.054974036,"remaining_time":3.212004523},
{"learn":[0.05301058769],"iteration":558,"passed_time":4.062301425,"remaining_time":3.204785203},
{"learn":[0.052973836],"iteration":559,"passed_time":4.069330394,"remaining_time":3.197331024},
{"learn":[0.05295898326],"iteration":560,"passed_time":4.075880356,"remaining_time":3.189503523},
{"learn":[0.05293134316],"iteration":561,"passed_time":4.084092965,"remaining_time":3.182976368},
{"learn":[0.05290411931],"iteration":562,"passed_time":4.091284352,"remaining_time":3.175650554},
{"learn":[0.0528761522],"iteration":563,"passed_time":4.098921495,"remaining_time":3.168669808},
{"learn":[0.05286367861],"iteration":564,"passed_time":4.105933172,"remaining_time":3.161205185},
{"learn":[0.05284982035],"iteration":565,"passed_time":4.113123059,"remaining_time":3.153878812},
{"learn":[0.05283038709],"iteration":566,"passed_time":4.120446157,"remaining_time":3.146654649},
{"learn":[0.05281035213],"iteration":567,"passed_time":4.127518459,"remaining_time":3.139239391},
{"learn":[0.05279535822],"iteration":568,"passed_time":4.134658095,"remaining_time":3.131876343},
{"learn":[0.05276656867],"iteration":569,"passed_time":4.142407115,"remaining_time":3.124973789},
{"learn":[0.05273497708],"iteration":570,"passed_time":4.150082426,"remaining_time":3.118012891},
{"learn":[0.05271453755],"iteration":571,"passed_time":4.15703331,"remaining_time":3.110507441},
{"learn":[0.05270458179],"iteration":572,"passed_time":4.163659856,"remaining_time":3.102762231},
{"learn":[0.05267192917],"iteration":573,"passed_time":4.170747492,"remaining_time":3.095363121},
{"learn":[0.05265915749],"iteration":574,"passed_time":4.177976505,"remaining_time":3.08806959},
{"learn":[0.05262954805],"iteration":575,"passed_time":4.185247435,"remaining_time":3.080807139},
{"learn":[0.0526144643],"iteration":576,"passed_time":4.192330821,"remaining_time":3.07340717},
{"learn":[0.05259891088],"iteration":577,"passed_time":4.199412873,"remaining_time":3.066007323},
{"learn":[0.05257851504],"iteration":578,"passed_time":4.206096462,"remaining_time":3.058318844},
{"learn":[0.05256636159],"iteration":579,"passed_time":4.213269349,"remaining_time":3.050988149},
{"learn":[0.05255165399],"iteration":580,"passed_time":4.220150482,"remaining_time":3.043447594},
{"learn":[0.05253465216],"iteration":581,"passed_time":4.227100324,"remaining_time":3.035958652},
{"learn":[0.05251928031],"iteration":582,"passed_time":4.234293628,"remaining_time":3.0286457},
{"learn":[0.05251226938],"iteration":583,"passed_time":4.241332264,"remaining_time":3.021222982},
{"learn":[0.05250000819],"iteration":584,"passed_time":4.248638569,"remaining_time":3.013991464},
{"learn":[0.05249263235],"iteration":585,"passed_time":4.255977,"remaining_time":3.006782386},
{"learn":[0.05248435031],"iteration":586,"passed_time":4.263204804,"remaining_time":2.999495033},
{"learn":[0.05246995813],"iteration":587,"passed_time":4.270548902,"remaining_time":2.992289367},
{"learn":[0.05245664986],"iteration":588,"passed_time":4.277689705,"remaining_time":2.984941373},
{"learn":[0.0524440835],"iteration":589,"passed_time":4.285448059,"remaining_time":2.978023227},
{"learn":[0.05242844642],"iteration":590,"passed_time":4.292698572,"remaining_time":2.970750788},
{"learn":[0.05241664459],"iteration":591,"passed_time":4.299912751,"remaining_time":2.963453382},
{"learn":[0.05240157524],"iteration":592,"passed_time":4.307134222,"remaining_time":2.956161262},
{"learn":[0.05238610177],"iteration":593,"passed_time":4.31397698,"remaining_time":2.948610528},
{"learn":[0.052371763],"iteration":594,"passed_time":4.321086782,"remaining_time":2.941243944},
{"learn":[0.05235710997],"iteration":595,"passed_time":4.328099459,"remaining_time":2.933812385},
{"learn":[0.05234398884],"iteration":596,"passed_time":4.33505701,"remaining_time":2.926345017},
{"learn":[0.05231942579],"iteration":597,"passed_time":4.342385232,"remaining_time":2.919128534},
{"learn":[0.05227566489],"iteration":598,"passed_time":4.349726288,"remaining_time":2.91192027},
{"learn":[0.05226060969],"iteration":599,"passed_time":4.357119303,"remaining_time":2.904746202},
{"learn":[0.05224720361],"iteration":600,"passed_time":4.364048104,"remaining_time":2.897263217},
{"learn":[0.05223477896],"iteration":601,"passed_time":4.371066822,"remaining_time":2.88984152},
{"learn":[0.05220408711],"iteration":602,"passed_time":4.378629131,"remaining_time":2.882779046},
{"learn":[0.05219137727],"iteration":603,"passed_time":4.38560339,"remaining_time":2.875329375},
{"learn":[0.05217057042],"iteration":604,"passed_time":4.392984905,"remaining_time":2.868147169},
{"learn":[0.05214925317],"iteration":605,"passed_time":4.400400129,"remaining_time":2.860986222},
{"learn":[0.05213333557],"iteration":606,"passed_time":4.407450847,"remaining_time":2.85358844},
{"learn":[0.05211868991],"iteration":607,"passed_time":4.414753236,"remaining_time":2.84635406},
{"learn":[0.05210588558],"iteration":608,"passed_time":4.422003541,"remaining_time":2.839086017},
{"learn":[0.05209138207],"iteration":609,"passed_time":4.429854812,"remaining_time":2.832202257},
{"learn":[0.05208628915],"iteration":610,"passed_time":4.436810363,"remaining_time":2.824745059},
{"learn":[0.05207106733],"iteration":611,"passed_time":4.443969708,"remaining_time":2.817418704},
{"learn":[0.05205811755],"iteration":612,"passed_time":4.45106801,"remaining_time":2.810054356},
{"learn":[0.05205183064],"iteration":613,"passed_time":4.458253981,"remaining_time":2.802745988},
{"learn":[0.05203625011],"iteration":614,"passed_time":4.465561203,"remaining_time":2.795513924},
{"learn":[0.05201439537],"iteration":615,"passed_time":4.472939426,"remaining_time":2.788325876},
{"learn":[0.05199480297],"iteration":616,"passed_time":4.480172231,"remaining_time":2.781046944},
{"learn":[0.05197879104],"iteration":617,"passed_time":4.487619246,"remaining_time":2.77390057},
{"learn":[0.05196223014],"iteration":618,"passed_time":4.494853801,"remaining_time":2.766622453},
{"learn":[0.05193000419],"iteration":619,"passed_time":4.502137106,"remaining_time":2.759374355},
{"learn":[0.05191780719],"iteration":620,"passed_time":4.509050531,"remaining_time":2.751900405},
{"learn":[0.05191214625],"iteration":621,"passed_time":4.5160745,"remaining_time":2.744495436},
{"learn":[0.05189258589],"iteration":622,"passed_time":4.522782256,"remaining_time":2.736900338},
{"learn":[0.05186572835],"iteration":623,"passed_time":4.529917225,"remaining_time":2.729565508},
{"learn":[0.05185457588],"iteration":624,"passed_time":4.536888651,"remaining_time":2.722133191},
{"learn":[0.05182470709],"iteration":625,"passed_time":4.544298667,"remaining_time":2.714964379},
{"learn":[0.05178646422],"iteration":626,"passed_time":4.552180896,"remaining_time":2.708075717},
{"learn":[0.0517646679],"iteration":627,"passed_time":4.560122585,"remaining_time":2.701219111},
{"learn":[0.05174884508],"iteration":628,"passed_time":4.566730548,"remaining_time":2.69357239},
{"learn":[0.05172512647],"iteration":629,"passed_time":4.573706558,"remaining_time":2.686145121},
{"learn":[0.05171199409],"iteration":630,"passed_time":4.580719526,"remaining_time":2.678740895},
{"learn":[0.0517020201],"iteration":631,"passed_time":4.587705369,"remaining_time":2.671322113},
{"learn":[0.05168852408],"iteration":632,"passed_time":4.595271344,"remaining_time":2.664241048},
{"learn":[0.05167525111],"iteration":633,"passed_time":4.602449231,"remaining_time":2.656934414},
{"learn":[0.05165885606],"iteration":634,"passed_time":4.609797954,"remaining_time":2.649726383},
{"learn":[0.05164479288],"iteration":635,"passed_time":4.616769755,"remaining_time":2.642302187},
{"learn":[0.05163102131],"iteration":636,"passed_time":4.623585762,"remaining_time":2.634790631},
{"learn":[0.05160335754],"iteration":637,"passed_time":4.63107007,"remaining_time":2.627660447},
{"learn":[0.05157325998],"iteration":638,"passed_time":4.638615629,"remaining_time":2.620563759},
{"learn":[0.05155124377],"iteration":639,"passed_time":4.645834683,"remaining_time":2.613282009},
{"learn":[0.05153300226],"iteration":640,"passed_time":4.653076321,"remaining_time":2.606013103},
{"learn":[0.05152402022],"iteration":641,"passed_time":4.660429836,"remaining_time":2.598806668},
{"learn":[0.05151257599],"iteration":642,"passed_time":4.667648265,"remaining_time":2.591524775},
{"learn":[0.05150127414],"iteration":643,"passed_time":4.674518523,"remaining_time":2.584050612},
{"learn":[0.05147818472],"iteration":644,"passed_time":4.68172391,"remaining_time":2.576762772},
{"learn":[0.05145919762],"iteration":645,"passed_time":4.689061133,"remaining_time":2.569547432},
{"learn":[0.05144786561],"iteration":646,"passed_time":4.697110448,"remaining_time":2.562720229},
{"learn":[0.05143194518],"iteration":647,"passed_time":4.704096291,"remaining_time":2.555311566},
{"learn":[0.05141060872],"iteration":648,"passed_time":4.711384513,"remaining_time":2.548067741},
{"learn":[0.05138353229],"iteration":649,"passed_time":4.718796778,"remaining_time":2.540890573},
{"learn":[0.05136068326],"iteration":650,"passed_time":4.726153668,"remaining_time":2.533682995},
{"learn":[0.0513384676],"iteration":651,"passed_time":4.73337268,"remaining_time":2.526401369},
{"learn":[0.05131936362],"iteration":652,"passed_time":4.740360773,"remaining_time":2.518997226},
{"learn":[0.05130634552],"iteration":653,"passed_time":4.747825039,"remaining_time":2.511846275},
{"learn":[0.05129404109],"iteration":654,"passed_time":4.75529843,"remaining_time":2.504699173},
{"learn":[0.05128527293],"iteration":655,"passed_time":4.762421983,"remaining_time":2.497367625},
{"learn":[0.05128144688],"iteration":656,"passed_time":4.769135281,"remaining_time":2.489822529},
{"learn":[0.05126987757],"iteration":657,"passed_time":4.776128082,"remaining_time":2.482425234},
{"learn":[0.05124709121],"iteration":658,"passed_time":4.783587556,"remaining_time":2.475270648},
{"learn":[0.05124174502],"iteration":659,"passed_time":4.790673692,"remaining_time":2.467922811},
{"learn":[0.05123571109],"iteration":660,"passed_time":4.798033373,"remaining_time":2.460716057},
{"learn":[0.05122027459],"iteration":661,"passed_time":4.805315137,"remaining_time":2.453469058},
{"learn":[0.05121276824],"iteration":662,"passed_time":4.812408065,"remaining_time":2.446125969},
{"learn":[0.05119230005],"iteration":663,"passed_time":4.819683245,"remaining_time":2.438875859},
{"learn":[0.05118114407],"iteration":664,"passed_time":4.827237553,"remaining_time":2.431766286},
{"learn":[0.05116897246],"iteration":665,"passed_time":4.834247897,"remaining_time":2.424382579},
{"learn":[0.05113773595],"iteration":666,"passed_time":4.841905915,"remaining_time":2.417323343},
{"learn":[0.05112789127],"iteration":667,"passed_time":4.849325847,"remaining_time":2.410143984},
{"learn":[0.05110111127],"iteration":668,"passed_time":4.856263606,"remaining_time":2.402725342},
{"learn":[0.051094605],"iteration":669,"passed_time":4.863087447,"remaining_time":2.395252026},
{"learn":[0.05106371893],"iteration":670,"passed_time":4.870492045,"remaining_time":2.388065399},
{"learn":[0.05104927032],"iteration":671,"passed_time":4.877000382,"remaining_time":2.380440662},
{"learn":[0.05103380263],"iteration":672,"passed_time":4.884068059,"remaining_time":2.373091018},
{"learn":[0.05102016742],"iteration":673,"passed_time":4.890942984,"remaining_time":2.36564898},
{"learn":[0.05097576808],"iteration":674,"passed_time":4.899380429,"remaining_time":2.358960947},
{"learn":[0.05095083735],"iteration":675,"passed_time":4.906812195,"remaining_time":2.351785726},
{"learn":[0.05093913495],"iteration":676,"passed_time":4.913869538,"remaining_time":2.344431109},
{"learn":[0.05091874242],"iteration":677,"passed_time":4.921234886,"remaining_time":2.337223648},
{"learn":[0.05089806661],"iteration":678,"passed_time":4.928582817,"remaining_time":2.330007488},
{"learn":[0.05088584429],"iteration":679,"passed_time":4.935833705,"remaining_time":2.322745273},
{"learn":[0.05087848295],"iteration":680,"passed_time":4.942721214,"remaining_time":2.315312874},
{"learn":[0.05086098803],"iteration":681,"passed_time":4.949902768,"remaining_time":2.308019179},
{"learn":[0.05084245703],"iteration":682,"passed_time":4.956994112,"remaining_time":2.300683944},
{"learn":[0.05083227599],"iteration":683,"passed_time":4.964203333,"remaining_time":2.293403879},
{"learn":[0.05081493471],"iteration":684,"passed_time":4.971217551,"remaining_time":2.286034348},
{"learn":[0.05080572531],"iteration":685,"passed_time":4.978437064,"remaining_time":2.278759822},
{"learn":[0.05079131649],"iteration":686,"passed_time":4.985483532,"remaining_time":2.271406617},
{"learn":[0.0507696966],"iteration":687,"passed_time":4.992726504,"remaining_time":2.264143414},
{"learn":[0.05076062284],"iteration":688,"passed_time":5.00022402,"remaining_time":2.256995167},
{"learn":[0.0507457114],"iteration":689,"passed_time":5.007408615,"remaining_time":2.24970532},
{"learn":[0.05073846166],"iteration":690,"passed_time":5.014491376,"remaining_time":2.242370239},
{"learn":[0.05073324041],"iteration":691,"passed_time":5.021814099,"remaining_time":2.235142691},
{"learn":[0.05072214163],"iteration":692,"passed_time":5.029290156,"remaining_time":2.227982797},
{"learn":[0.05070568578],"iteration":693,"passed_time":5.036308916,"remaining_time":2.220620358},
{"learn":[0.05068539011],"iteration":694,"passed_time":5.043830225,"remaining_time":2.213479451},
{"learn":[0.05067190494],"iteration":695,"passed_time":5.051089488,"remaining_time":2.206222995},
{"learn":[0.05065682138],"iteration":696,"passed_time":5.057882536,"remaining_time":2.198763857},
{"learn":[0.05064258915],"iteration":697,"passed_time":5.065378178,"remaining_time":2.191610616},
{"learn":[0.05063022573],"iteration":698,"passed_time":5.072327103,"remaining_time":2.18422097},
{"learn":[0.05061928404],"iteration":699,"passed_time":5.078989942,"remaining_time":2.176709975},
{"learn":[0.05059745662],"iteration":700,"passed_time":5.085956118,"remaining_time":2.169330784},
{"learn":[0.05057769972],"iteration":701,"passed_time":5.093304716,"remaining_time":2.162115107},
{"learn":[0.05055879886],"iteration":702,"passed_time":5.100737148,"remaining_time":2.154934471},
{"learn":[0.05053596403],"iteration":703,"passed_time":5.108880048,"remaining_time":2.148051838},
{"learn":[0.05052970162],"iteration":704,"passed_time":5.115755806,"remaining_time":2.140635408},
{"learn":[0.05051125896],"iteration":705,"passed_time":5.122797358,"remaining_time":2.133289551},
{"learn":[0.05049990146],"iteration":706,"passed_time":5.130044371,"remaining_time":2.126029704},
{"learn":[0.05048260508],"iteration":707,"passed_time":5.137416219,"remaining_time":2.118821378},
{"learn":[0.05045162311],"iteration":708,"passed_time":5.144955736,"remaining_time":2.111681409},
{"learn":[0.05044298005],"iteration":709,"passed_time":5.151950704,"remaining_time":2.104317893},
{"learn":[0.05042749872],"iteration":710,"passed_time":5.159433553,"remaining_time":2.097153723},
{"learn":[0.05040239265],"iteration":711,"passed_time":5.167187823,"remaining_time":2.090098445},
{"learn":[0.05038723208],"iteration":712,"passed_time":5.174116332,"remaining_time":2.082708818},
{"learn":[0.05038327105],"iteration":713,"passed_time":5.180940631,"remaining_time":2.07527874},
{"learn":[0.0503746979],"iteration":714,"passed_time":5.188142352,"remaining_time":2.068000797},
{"learn":[0.05035337698],"iteration":715,"passed_time":5.195398865,"remaining_time":2.060744801},
{"learn":[0.05034152494],"iteration":716,"passed_time":5.202585252,"remaining_time":2.053461125},
{"learn":[0.05032763789],"iteration":717,"passed_time":5.209809681,"remaining_time":2.04619266},
{"learn":[0.05032016286],"iteration":718,"passed_time":5.21663323,"remaining_time":2.038767646},
{"learn":[0.05031032719],"iteration":719,"passed_time":5.223992245,"remaining_time":2.03155254},
{"learn":[0.05030152742],"iteration":720,"passed_time":5.231338843,"remaining_time":2.024332229},
{"learn":[0.05028916895],"iteration":721,"passed_time":5.238541355,"remaining_time":2.01705609},
{"learn":[0.05027662174],"iteration":722,"passed_time":5.24542028,"remaining_time":2.009656179},
{"learn":[0.05026552674],"iteration":723,"passed_time":5.252354455,"remaining_time":2.00227877},
{"learn":[0.05025380414],"iteration":724,"passed_time":5.259361382,"remaining_time":1.994930179},
{"learn":[0.05024446666],"iteration":725,"passed_time":5.266052971,"remaining_time":1.987463518},
{"learn":[0.05022528307],"iteration":726,"passed_time":5.273181107,"remaining_time":1.980162919},
{"learn":[0.0501974372],"iteration":727,"passed_time":5.280979503,"remaining_time":1.973113221},
{"learn":[0.05017524355],"iteration":728,"passed_time":5.288393559,"remaining_time":1.965918593},
{"learn":[0.05016681879],"iteration":729,"passed_time":5.29545457,"remaining_time":1.958592786},
{"learn":[0.05014691092],"iteration":730,"passed_time":5.302376495,"remaining_time":1.951216522},
{"learn":[0.05014136225],"iteration":731,"passed_time":5.309707009,"remaining_time":1.943991091},
{"learn":[0.05013657347],"iteration":732,"passed_time":5.31652285,"remaining_time":1.9365779},
{"learn":[0.05012497431],"iteration":733,"passed_time":5.323524485,"remaining_time":1.929233669},
{"learn":[0.05011790933],"iteration":734,"passed_time":5.330672997,"remaining_time":1.921943325},
{"learn":[0.05009382912],"iteration":735,"passed_time":5.338286931,"remaining_time":1.914820312},
{"learn":[0.05008354513],"iteration":736,"passed_time":5.345424151,"remaining_time":1.90752585},
{"learn":[0.05007100119],"iteration":737,"passed_time":5.35251537,"remaining_time":1.900215484},
{"learn":[0.05005555758],"iteration":738,"passed_time":5.359250168,"remaining_time":1.892779829},
{"learn":[0.05002541744],"iteration":739,"passed_time":5.366782018,"remaining_time":1.885626115},
{"learn":[0.05001882944],"iteration":740,"passed_time":5.373883779,"remaining_time":1.878321051},
{"learn":[0.04999732293],"iteration":741,"passed_time":5.381000082,"remaining_time":1.871021592},
{"learn":[0.04997979567],"iteration":742,"passed_time":5.388271262,"remaining_time":1.863776197},
{"learn":[0.04997420321],"iteration":743,"passed_time":5.395267064,"remaining_time":1.856435979},
{"learn":[0.04996146364],"iteration":744,"passed_time":5.402298699,"remaining_time":1.849108951},
{"learn":[0.04993218017],"iteration":745,"passed_time":5.409513961,"remaining_time":1.841845236},
{"learn":[0.04991724591],"iteration":746,"passed_time":5.416914018,"remaining_time":1.834644239},
{"learn":[0.0499020705],"iteration":747,"passed_time":5.423969737,"remaining_time":1.827326703},
{"learn":[0.04988387407],"iteration":748,"passed_time":5.430773702,"remaining_time":1.8199255},
{"learn":[0.04987366756],"iteration":749,"passed_time":5.437914714,"remaining_time":1.812638238},
{"learn":[0.04985944492],"iteration":750,"passed_time":5.444835473,"remaining_time":1.805278339},
{"learn":[0.04983618341],"iteration":751,"passed_time":5.451980318,"remaining_time":1.797993509},
{"learn":[0.04982258561],"iteration":752,"passed_time":5.459263998,"remaining_time":1.790754592},
{"learn":[0.04979324691],"iteration":753,"passed_time":5.466695347,"remaining_time":1.783563734},
{"learn":[0.04978219069],"iteration":754,"passed_time":5.473837817,"remaining_time":1.776278497},
{"learn":[0.04976861662],"iteration":755,"passed_time":5.480869243,"remaining_time":1.768957798},
{"learn":[0.04974279955],"iteration":756,"passed_time":5.488253883,"remaining_time":1.761751247},
{"learn":[0.0497220641],"iteration":757,"passed_time":5.495340352,"remaining_time":1.754449031},
{"learn":[0.04971211672],"iteration":758,"passed_time":5.50227807,"remaining_time":1.747100151},
{"learn":[0.04970058097],"iteration":759,"passed_time":5.509733502,"remaining_time":1.739915843},
{"learn":[0.04968522207],"iteration":760,"passed_time":5.517291936,"remaining_time":1.73276317},
{"learn":[0.04967619037],"iteration":761,"passed_time":5.524162319,"remaining_time":1.72539453},
{"learn":[0.04966803988],"iteration":762,"passed_time":5.531013452,"remaining_time":1.718021216},
{"learn":[0.04965235815],"iteration":763,"passed_time":5.53774125,"remaining_time":1.710611171},
{"learn":[0.04962875621],"iteration":764,"passed_time":5.54488672,"remaining_time":1.703331214},
{"learn":[0.04960803649],"iteration":765,"passed_time":5.552106857,"remaining_time":1.696074419},
{"learn":[0.0495863077],"iteration":766,"passed_time":5.559101617,"remaining_time":1.688749253},
{"learn":[0.04957368727],"iteration":767,"passed_time":5.566278337,"remaining_time":1.681479914},
{"learn":[0.04956392623],"iteration":768,"passed_time":5.573026719,"remaining_time":1.674082148},
{"learn":[0.04953376943],"iteration":769,"passed_time":5.580185064,"remaining_time":1.666808526},
{"learn":[0.04952195556],"iteration":770,"passed_time":5.587128573,"remaining_time":1.659471392},
{"learn":[0.04951450243],"iteration":771,"passed_time":5.593915746,"remaining_time":1.652089106},
{"learn":[0.04948851544],"iteration":772,"passed_time":5.601143967,"remaining_time":1.644837879},
{"learn":[0.04948428397],"iteration":773,"passed_time":5.607817973,"remaining_time":1.637424886},
{"learn":[0.04946206878],"iteration":774,"passed_time":5.615001277,"remaining_time":1.630161661},
{"learn":[0.04945324434],"iteration":775,"passed_time":5.622132705,"remaining_time":1.622883667},
{"learn":[0.04943242969],"iteration":776,"passed_time":5.629413427,"remaining_time":1.615648899},
{"learn":[0.04942101338],"iteration":777,"passed_time":5.636374144,"remaining_time":1.608322699},
{"learn":[0.04939865802],"iteration":778,"passed_time":5.643808201,"remaining_time":1.601131723},
{"learn":[0.04937624656],"iteration":779,"passed_time":5.650981088,"remaining_time":1.593866461},
{"learn":[0.04935391138],"iteration":780,"passed_time":5.658063058,"remaining_time":1.586575941},
{"learn":[0.04933676615],"iteration":781,"passed_time":5.665484781,"remaining_time":1.579380668},
{"learn":[0.04933478615],"iteration":782,"passed_time":5.671722864,"remaining_time":1.571856784},
{"learn":[0.049313678],"iteration":783,"passed_time":5.678643873,"remaining_time":1.564524332},
{"learn":[0.04930166268],"iteration":784,"passed_time":5.686111514,"remaining_time":1.557342644},
{"learn":[0.0492844806],"iteration":785,"passed_time":5.693129774,"remaining_time":1.550037877},
{"learn":[0.04926621754],"iteration":786,"passed_time":5.700366953,"remaining_time":1.542793089},
{"learn":[0.0492467445],"iteration":787,"passed_time":5.707454631,"remaining_time":1.535508099},
{"learn":[0.04923694667],"iteration":788,"passed_time":5.714894271,"remaining_time":1.528317733},
{"learn":[0.04920847596],"iteration":789,"passed_time":5.721990407,"remaining_time":1.521035425},
{"learn":[0.04919746222],"iteration":790,"passed_time":5.730971069,"remaining_time":1.514251521},
{"learn":[0.04919184665],"iteration":791,"passed_time":5.73933943,"remaining_time":1.507301264},
{"learn":[0.04918643683],"iteration":792,"passed_time":5.746484775,"remaining_time":1.500028182},
{"learn":[0.0491682358],"iteration":793,"passed_time":5.753663829,"remaining_time":1.492764167},
{"learn":[0.0491500209],"iteration":794,"passed_time":5.760664963,"remaining_time":1.485454487},
{"learn":[0.04914988669],"iteration":795,"passed_time":5.766349289,"remaining_time":1.477808109},
{"learn":[0.04913395108],"iteration":796,"passed_time":5.773536301,"remaining_time":1.470549397},
{"learn":[0.04912032594],"iteration":797,"passed_time":5.781006317,"remaining_time":1.463362501},
{"learn":[0.04911263871],"iteration":798,"passed_time":5.788299997,"remaining_time":1.456130538},
{"learn":[0.04909831412],"iteration":799,"passed_time":5.795725429,"remaining_time":1.448931357},
{"learn":[0.04907812849],"iteration":800,"passed_time":5.803140736,"remaining_time":1.441729097},
{"learn":[0.04906205705],"iteration":801,"passed_time":5.810668836,"remaining_time":1.434554152},
{"learn":[0.04905362448],"iteration":802,"passed_time":5.817442176,"remaining_time":1.427193162},
{"learn":[0.04904461331],"iteration":803,"passed_time":5.824576063,"remaining_time":1.419921528},
{"learn":[0.04903252774],"iteration":804,"passed_time":5.831762075,"remaining_time":1.412662863},
{"learn":[0.04901673186],"iteration":805,"passed_time":5.83948897,"remaining_time":1.405534566},
{"learn":[0.04900660173],"iteration":806,"passed_time":5.846880318,"remaining_time":1.398324537},
{"learn":[0.0489924201],"iteration":807,"passed_time":5.854053663,"remaining_time":1.391062257},
{"learn":[0.04897459143],"iteration":808,"passed_time":5.860767544,"remaining_time":1.383691719},
{"learn":[0.04896452886],"iteration":809,"passed_time":5.867815055,"remaining_time":1.376401062},
{"learn":[0.04895350281],"iteration":810,"passed_time":5.874925107,"remaining_time":1.36912558},
{"learn":[0.048947706],"iteration":811,"passed_time":5.882018368,"remaining_time":1.361846617},
{"learn":[0.04894278742],"iteration":812,"passed_time":5.889127588,"remaining_time":1.354571782},
{"learn":[0.04893158887],"iteration":813,"passed_time":5.896468144,"remaining_time":1.347350215},
{"learn":[0.04892036389],"iteration":814,"passed_time":5.903316818,"remaining_time":1.340016701},
{"learn":[0.04889442792],"iteration":815,"passed_time":5.910770001,"remaining_time":1.332820686},
{"learn":[0.04888171545],"iteration":816,"passed_time":5.917580841,"remaining_time":1.325480164},
{"learn":[0.04884299691],"iteration":817,"passed_time":5.924815437,"remaining_time":1.31823522},
{"learn":[0.04882895809],"iteration":818,"passed_time":5.932054617,"remaining_time":1.310991313},
{"learn":[0.04880202117],"iteration":819,"passed_time":5.939316922,"remaining_time":1.303752495},
{"learn":[0.04878184302],"iteration":820,"passed_time":5.946147721,"remaining_time":1.29641954},
{"learn":[0.04875556093],"iteration":821,"passed_time":5.953765406,"remaining_time":1.289258202},
{"learn":[0.04874699753],"iteration":822,"passed_time":5.960719623,"remaining_time":1.281953066},
{"learn":[0.04872848329],"iteration":823,"passed_time":5.967748966,"remaining_time":1.274664828},
{"learn":[0.04871688529],"iteration":824,"passed_time":5.97452464,"remaining_time":1.267323408},
{"learn":[0.04870632933],"iteration":825,"passed_time":5.981539816,"remaining_time":1.260033811},
{"learn":[0.04868465811],"iteration":826,"passed_time":5.988533451,"remaining_time":1.252740371},
{"learn":[0.04867396986],"iteration":827,"passed_time":5.995473252,"remaining_time":1.245436473},
{"learn":[0.04865616076],"iteration":828,"passed_time":6.002721015,"remaining_time":1.238196977},
{"learn":[0.04864360033],"iteration":829,"passed_time":6.010357158,"remaining_time":1.231037008},
{"learn":[0.0486389503],"iteration":830,"passed_time":6.01717204,"remaining_time":1.223708875},
{"learn":[0.04863197813],"iteration":831,"passed_time":6.024034423,"remaining_time":1.216391566},
{"learn":[0.04861718933],"iteration":832,"passed_time":6.031191768,"remaining_time":1.209134484},
{"learn":[0.04859759148],"iteration":833,"passed_time":6.038455198,"remaining_time":1.201898756},
{"learn":[0.04859416345],"iteration":834,"passed_time":6.04570067,"remaining_time":1.194659414},
{"learn":[0.04856924706],"iteration":835,"passed_time":6.053389063,"remaining_time":1.187506945},
{"learn":[0.04855880638],"iteration":836,"passed_time":6.060417282,"remaining_time":1.180224632},
{"learn":[0.04854593982],"iteration":837,"passed_time":6.067496626,"remaining_time":1.172952808},
{"learn":[0.04853551637],"iteration":838,"passed_time":6.074397634,"remaining_time":1.165647222},
{"learn":[0.0485282212],"iteration":839,"passed_time":6.081924234,"remaining_time":1.158461759},
{"learn":[0.04851494984],"iteration":840,"passed_time":6.088998912,"remaining_time":1.151190044},
{"learn":[0.04849899492],"iteration":841,"passed_time":6.095863253,"remaining_time":1.143879328},
{"learn":[0.04848296538],"iteration":842,"passed_time":6.10299139,"remaining_time":1.1366188},
{"learn":[0.04847216471],"iteration":843,"passed_time":6.110356404,"remaining_time":1.129402369},
{"learn":[0.0484621854],"iteration":844,"passed_time":6.117790503,"remaining_time":1.122198258},
{"learn":[0.04845202034],"iteration":845,"passed_time":6.124497925,"remaining_time":1.114861324},
{"learn":[0.04842120496],"iteration":846,"passed_time":6.132645575,"remaining_time":1.107786037},
{"learn":[0.04840883492],"iteration":847,"passed_time":6.140016007,"remaining_time":1.100568907},
{"learn":[0.04839457372],"iteration":848,"passed_time":6.147145518,"remaining_time":1.093308567},
{"learn":[0.04838404504],"iteration":849,"passed_time":6.154237946,"remaining_time":1.08604199},
{"learn":[0.04837138127],"iteration":850,"passed_time":6.161357749,"remaining_time":1.078780616},
{"learn":[0.04835697529],"iteration":851,"passed_time":6.168752139,"remaining_time":1.071567273},
{"learn":[0.04834925629],"iteration":852,"passed_time":6.175588021,"remaining_time":1.064257256},
{"learn":[0.04832712757],"iteration":853,"passed_time":6.182938411,"remaining_time":1.057036309},
{"learn":[0.0483121393],"iteration":854,"passed_time":6.190111256,"remaining_time":1.04978495},
{"learn":[0.04829973865],"iteration":855,"passed_time":6.197367811,"remaining_time":1.042547856},
{"learn":[0.04829240552],"iteration":856,"passed_time":6.204531698,"remaining_time":1.035295254},
{"learn":[0.04828016467],"iteration":857,"passed_time":6.211525624,"remaining_time":1.02801473},
{"learn":[0.04827010962],"iteration":858,"passed_time":6.218575843,"remaining_time":1.020744114},
{"learn":[0.04825690443],"iteration":859,"passed_time":6.226214153,"remaining_time":1.013569746},
{"learn":[0.04824480652],"iteration":860,"passed_time":6.23328708,"remaining_time":1.006303025},
{"learn":[0.04823049854],"iteration":861,"passed_time":6.240097004,"remaining_time":0.998994648},
{"learn":[0.04821680601],"iteration":862,"passed_time":6.247267391,"remaining_time":0.9917446496},
{"learn":[0.04820547334],"iteration":863,"passed_time":6.254623072,"remaining_time":0.9845240021},
{"learn":[0.04819886568],"iteration":864,"passed_time":6.261534581,"remaining_time":0.9772337207},
{"learn":[0.048183658],"iteration":865,"passed_time":6.269459186,"remaining_time":0.970101075},
{"learn":[0.04816153073],"iteration":866,"passed_time":6.276715199,"remaining_time":0.9628640386},
{"learn":[0.04814701156],"iteration":867,"passed_time":6.284749306,"remaining_time":0.9557452862},
{"learn":[0.04812309328],"iteration":868,"passed_time":6.291500854,"remaining_time":0.9484310839},
{"learn":[0.0481211813],"iteration":869,"passed_time":6.298196068,"remaining_time":0.9411097573},
{"learn":[0.04810602291],"iteration":870,"passed_time":6.305383414,"remaining_time":0.9338627559},
{"learn":[0.04809596286],"iteration":871,"passed_time":6.312609676,"remaining_time":0.9266216039},
{"learn":[0.04809343637],"iteration":872,"passed_time":6.319504935,"remaining_time":0.919332333},
{"learn":[0.0480778406],"iteration":873,"passed_time":6.326662863,"remaining_time":0.9120818315},
{"learn":[0.04806049242],"iteration":874,"passed_time":6.335409313,"remaining_time":0.9050584733},
{"learn":[0.04805695731],"iteration":875,"passed_time":6.342503157,"remaining_time":0.8977972506},
{"learn":[0.04803268623],"iteration":876,"passed_time":6.349777671,"remaining_time":0.8905617486},
{"learn":[0.04801182991],"iteration":877,"passed_time":6.356946058,"remaining_time":0.8833114112},
{"learn":[0.04799659898],"iteration":878,"passed_time":6.364017902,"remaining_time":0.8760479705},
{"learn":[0.04797244308],"iteration":879,"passed_time":6.371292457,"remaining_time":0.8688126077},
{"learn":[0.04796124078],"iteration":880,"passed_time":6.378330842,"remaining_time":0.8615452556},
{"learn":[0.04793562979],"iteration":881,"passed_time":6.385037806,"remaining_time":0.8542340829},
{"learn":[0.04792066501],"iteration":882,"passed_time":6.392574698,"remaining_time":0.8470342465},
{"learn":[0.04791186548],"iteration":883,"passed_time":6.399575791,"remaining_time":0.8397633391},
{"learn":[0.04789016701],"iteration":884,"passed_time":6.406586718,"remaining_time":0.8324943192},
{"learn":[0.04787794148],"iteration":885,"passed_time":6.41382798,"remaining_time":0.8252555189},
{"learn":[0.04787567517],"iteration":886,"passed_time":6.420883116,"remaining_time":0.8179930012},
{"learn":[0.04786354881],"iteration":887,"passed_time":6.427623456,"remaining_time":0.8106912466},
{"learn":[0.04785139092],"iteration":888,"passed_time":6.435617228,"remaining_time":0.803547258},
{"learn":[0.04783087026],"iteration":889,"passed_time":6.443088286,"remaining_time":0.7963367545},
{"learn":[0.04780974253],"iteration":890,"passed_time":6.450662679,"remaining_time":0.7891383075},
{"learn":[0.04778904318],"iteration":891,"passed_time":6.457773315,"remaining_time":0.7818828677},
{"learn":[0.04777433438],"iteration":892,"passed_time":6.464385653,"remaining_time":0.7745680457},
{"learn":[0.04776531955],"iteration":893,"passed_time":6.471212285,"remaining_time":0.7672802038},
{"learn":[0.04775376672],"iteration":894,"passed_time":6.478305713,"remaining_time":0.7600246926},
{"learn":[0.04774644711],"iteration":895,"passed_time":6.48528268,"remaining_time":0.7527560254},
{"learn":[0.04773577957],"iteration":896,"passed_time":6.492222023,"remaining_time":0.7454836882},
{"learn":[0.04770220746],"iteration":897,"passed_time":6.49978329,"remaining_time":0.7382827345},
{"learn":[0.04769112735],"iteration":898,"passed_time":6.506886343,"remaining_time":0.7310295001},
{"learn":[0.04766453807],"iteration":899,"passed_time":6.51431765,"remaining_time":0.7238130722},
{"learn":[0.04765125742],"iteration":900,"passed_time":6.521559329,"remaining_time":0.7165753314},
{"learn":[0.04763354212],"iteration":901,"passed_time":6.528354545,"remaining_time":0.7092890747},
{"learn":[0.04761743814],"iteration":902,"passed_time":6.535710226,"remaining_time":0.7020641106},
{"learn":[0.04760783942],"iteration":903,"passed_time":6.54356033,"remaining_time":0.6948913625},
{"learn":[0.04758101456],"iteration":904,"passed_time":6.551137098,"remaining_time":0.6876884246},
{"learn":[0.04755673452],"iteration":905,"passed_time":6.558177358,"remaining_time":0.6804289974},
{"learn":[0.04754743256],"iteration":906,"passed_time":6.565040824,"remaining_time":0.6731519257},
{"learn":[0.04753171521],"iteration":907,"passed_time":6.572178461,"remaining_time":0.6659035445},
{"learn":[0.04750925611],"iteration":908,"passed_time":6.579288097,"remaining_time":0.6586526038},
{"learn":[0.04749574641],"iteration":909,"passed_time":6.58665032,"remaining_time":0.6514269547},
{"learn":[0.04748323724],"iteration":910,"passed_time":6.593943458,"remaining_time":0.6441942566},
{"learn":[0.04746989452],"iteration":911,"passed_time":6.60069109,"remaining_time":0.6369087894},
{"learn":[0.04746149741],"iteration":912,"passed_time":6.607714142,"remaining_time":0.6296507451},
{"learn":[0.04745345327],"iteration":913,"passed_time":6.615061489,"remaining_time":0.6224237287},
{"learn":[0.04744223902],"iteration":914,"passed_time":6.621947831,"remaining_time":0.6151536236},
{"learn":[0.04743059232],"iteration":915,"passed_time":6.628826089,"remaining_time":0.6078836151},
{"learn":[0.04743057459],"iteration":916,"passed_time":6.634728751,"remaining_time":0.6005261574},
{"learn":[0.04741180394],"iteration":917,"passed_time":6.642522896,"remaining_time":0.5933408251},
{"learn":[0.04740611923],"iteration":918,"passed_time":6.649749534,"remaining_time":0.5861041482},
{"learn":[0.04738910126],"iteration":919,"passed_time":6.656665542,"remaining_time":0.5788404819},
{"learn":[0.04738015335],"iteration":920,"passed_time":6.663867305,"remaining_time":0.5716020815},
{"learn":[0.0473671517],"iteration":921,"passed_time":6.671039942,"remaining_time":0.5643612966},
{"learn":[0.047367111],"iteration":922,"passed_time":6.676778518,"remaining_time":0.5570010248},
{"learn":[0.04736706817],"iteration":923,"passed_time":6.682559845,"remaining_time":0.5496477795},
{"learn":[0.04736500371],"iteration":924,"passed_time":6.68899343,"remaining_time":0.5423508187},
{"learn":[0.04734894459],"iteration":925,"passed_time":6.696058941,"remaining_time":0.5351062221},
{"learn":[0.04733070014],"iteration":926,"passed_time":6.703047451,"remaining_time":0.5278559481},
{"learn":[0.04733051816],"iteration":927,"passed_time":6.709591538,"remaining_time":0.5205717572},
{"learn":[0.0473147361],"iteration":928,"passed_time":6.716691132,"remaining_time":0.513331615},
{"learn":[0.04731472255],"iteration":929,"passed_time":6.722423042,"remaining_time":0.5059888311},
{"learn":[0.04730708709],"iteration":930,"passed_time":6.729391009,"remaining_time":0.4987411167},
{"learn":[0.0473006795],"iteration":931,"passed_time":6.736392019,"remaining_time":0.4914964134},
{"learn":[0.04729343324],"iteration":932,"passed_time":6.743969911,"remaining_time":0.4842936592},
{"learn":[0.04727902214],"iteration":933,"passed_time":6.75197831,"remaining_time":0.4771205229},
{"learn":[0.04726459154],"iteration":934,"passed_time":6.759377075,"remaining_time":0.4699032191},
{"learn":[0.04725563166],"iteration":935,"passed_time":6.766282625,"remaining_time":0.4626518034},
{"learn":[0.04724088074],"iteration":936,"passed_time":6.773187008,"remaining_time":0.4554010475},
{"learn":[0.04722984784],"iteration":937,"passed_time":6.780183476,"remaining_time":0.4481571168},
{"learn":[0.04722119149],"iteration":938,"passed_time":6.787310904,"remaining_time":0.4409222206},
{"learn":[0.04722117495],"iteration":939,"passed_time":6.792984105,"remaining_time":0.4335947301},
{"learn":[0.04720482083],"iteration":940,"passed_time":6.800059824,"remaining_time":0.4263586925},
{"learn":[0.04719414441],"iteration":941,"passed_time":6.807077959,"remaining_time":0.4191194497},
{"learn":[0.04718546409],"iteration":942,"passed_time":6.814135136,"remaining_time":0.4118830358},
{"learn":[0.04717838768],"iteration":943,"passed_time":6.821262356,"remaining_time":0.4046511567},
{"learn":[0.04716211518],"iteration":944,"passed_time":6.828622203,"remaining_time":0.3974330383},
{"learn":[0.04715749293],"iteration":945,"passed_time":6.835268375,"remaining_time":0.3901738819},
{"learn":[0.04714156445],"iteration":946,"passed_time":6.842412429,"remaining_time":0.3829438846},
{"learn":[0.04712952045],"iteration":947,"passed_time":6.849577857,"remaining_time":0.3757152411},
{"learn":[0.04712132348],"iteration":948,"passed_time":6.857016039,"remaining_time":0.3685013888},
{"learn":[0.04711252822],"iteration":949,"passed_time":6.863915214,"remaining_time":0.3612586955},
{"learn":[0.04710634453],"iteration":950,"passed_time":6.871159269,"remaining_time":0.3540344944},
{"learn":[0.04708829058],"iteration":951,"passed_time":6.8778964,"remaining_time":0.3467846925},
{"learn":[0.04707732489],"iteration":952,"passed_time":6.884951827,"remaining_time":0.3395516641},
{"learn":[0.04706434111],"iteration":953,"passed_time":6.89165575,"remaining_time":0.3323020592},
{"learn":[0.0470512225],"iteration":954,"passed_time":6.898879763,"remaining_time":0.325078104},
{"learn":[0.04704093482],"iteration":955,"passed_time":6.906004899,"remaining_time":0.3178495979},
{"learn":[0.04703637235],"iteration":956,"passed_time":6.91334258,"remaining_time":0.3106308578},
{"learn":[0.0470363545],"iteration":957,"passed_time":6.918900487,"remaining_time":0.3033338418},
{"learn":[0.04702794412],"iteration":958,"passed_time":6.925849954,"remaining_time":0.2960999459},
{"learn":[0.0470242505],"iteration":959,"passed_time":6.932623711,"remaining_time":0.2888593213},
{"learn":[0.04701494745],"iteration":960,"passed_time":6.939754723,"remaining_time":0.2816341667},
{"learn":[0.04700671424],"iteration":961,"passed_time":6.947196947,"remaining_time":0.274421501},
{"learn":[0.04698842612],"iteration":962,"passed_time":6.954789423,"remaining_time":0.2672141315},
{"learn":[0.04696899762],"iteration":963,"passed_time":6.961984727,"remaining_time":0.2599911309},
{"learn":[0.04696138397],"iteration":964,"passed_time":6.969121405,"remaining_time":0.2527660613},
{"learn":[0.04695496848],"iteration":965,"passed_time":6.97650567,"remaining_time":0.245549889},
{"learn":[0.04694864984],"iteration":966,"passed_time":6.983568264,"remaining_time":0.2383223916},
{"learn":[0.04693884432],"iteration":967,"passed_time":6.990656108,"remaining_time":0.2310960697},
{"learn":[0.04692972621],"iteration":968,"passed_time":6.997660451,"remaining_time":0.2238673622},
{"learn":[0.04692116286],"iteration":969,"passed_time":7.004957465,"remaining_time":0.216648169},
{"learn":[0.04691494326],"iteration":970,"passed_time":7.012322646,"remaining_time":0.2094308514},
{"learn":[0.04690723053],"iteration":971,"passed_time":7.019211529,"remaining_time":0.2021995091},
{"learn":[0.0468916801],"iteration":972,"passed_time":7.026594044,"remaining_time":0.1949825685},
{"learn":[0.04688790794],"iteration":973,"passed_time":7.033413176,"remaining_time":0.1877502491},
{"learn":[0.04687892597],"iteration":974,"passed_time":7.040646314,"remaining_time":0.1805293927},
{"learn":[0.04687885511],"iteration":975,"passed_time":7.046511809,"remaining_time":0.1732748805},
{"learn":[0.04687091531],"iteration":976,"passed_time":7.053443359,"remaining_time":0.1660483084},
{"learn":[0.04685833283],"iteration":977,"passed_time":7.061089461,"remaining_time":0.1588384132},
{"learn":[0.04685113773],"iteration":978,"passed_time":7.068386558,"remaining_time":0.1516201407},
{"learn":[0.04683647843],"iteration":979,"passed_time":7.075277483,"remaining_time":0.144393418},
{"learn":[0.04682966796],"iteration":980,"passed_time":7.082443453,"remaining_time":0.137172707},
{"learn":[0.04682293985],"iteration":981,"passed_time":7.089467296,"remaining_time":0.1299495024},
{"learn":[0.04681886999],"iteration":982,"passed_time":7.096510432,"remaining_time":0.122727037},
{"learn":[0.04681122784],"iteration":983,"passed_time":7.103560734,"remaining_time":0.1155050526},
{"learn":[0.04680475926],"iteration":984,"passed_time":7.110377866,"remaining_time":0.108279866},
{"learn":[0.04679790602],"iteration":985,"passed_time":7.117262291,"remaining_time":0.1010564625},
{"learn":[0.046788997],"iteration":986,"passed_time":7.124230759,"remaining_time":0.09383485295},
{"learn":[0.04678295696],"iteration":987,"passed_time":7.130888097,"remaining_time":0.08660997689},
{"learn":[0.04676253706],"iteration":988,"passed_time":7.138244362,"remaining_time":0.07939402222},
{"learn":[0.04675049376],"iteration":989,"passed_time":7.145524375,"remaining_time":0.07217701389},
{"learn":[0.04674261007],"iteration":990,"passed_time":7.152735346,"remaining_time":0.06495925138},
{"learn":[0.04672732161],"iteration":991,"passed_time":7.160206862,"remaining_time":0.05774360373},
{"learn":[0.04671769337],"iteration":992,"passed_time":7.167572793,"remaining_time":0.05052669643},
{"learn":[0.04670887926],"iteration":993,"passed_time":7.174715388,"remaining_time":0.04330814118},
{"learn":[0.04670021979],"iteration":994,"passed_time":7.181578854,"remaining_time":0.03608833595},
{"learn":[0.04668115806],"iteration":995,"passed_time":7.188925327,"remaining_time":0.02887118605},
{"learn":[0.04667292666],"iteration":996,"passed_time":7.196049338,"remaining_time":0.02165310734},
{"learn":[0.04666110832],"iteration":997,"passed_time":7.203232226,"remaining_time":0.01443533512},
{"learn":[0.04665581212],"iteration":998,"passed_time":7.210170401,"remaining_time":0.007217387789},
{"learn":[0.04664080734],"iteration":999,"passed_time":7.217259037,"remaining_time":0}
]}